Workbook

Sheet Run Overview
B2: GO Website Manual QA 1.9
B3: Prepared 28 October 2026. New results have not been executed.
B5: Current run | F5: Run details to complete
B6: Total cases | C6: =COUNTA('V 1.9 TEST'!$B$2:$B$1000) -> 674 | F6: Test environment | G6: To complete
B7: Pass | C7: =COUNTIFS('V 1.9 TEST'!$A$2:$A$1000,"Pass",'V 1.9 TEST'!$B$2:$B$1000,"<>") -> 0 | F7: Base URL
B8: Fail | C8: =COUNTIFS('V 1.9 TEST'!$A$2:$A$1000,"Fail",'V 1.9 TEST'!$B$2:$B$1000,"<>") -> 0 | F8: Deployed build / commit
B9: Blocked | C9: =COUNTIFS('V 1.9 TEST'!$A$2:$A$1000,"Blocked",'V 1.9 TEST'!$B$2:$B$1000,"<>") -> 0 | F9: Tester / lead
B10: Retest | C10: =COUNTIFS('V 1.9 TEST'!$A$2:$A$1000,"Retest",'V 1.9 TEST'!$B$2:$B$1000,"<>") -> 0 | F10: Run started
B11: Not Run | C11: =COUNTIFS('V 1.9 TEST'!$A$2:$A$1000,"Not Run",'V 1.9 TEST'!$B$2:$B$1000,"<>") -> 674 | F11: Run finished
B12: N/A | C12: =COUNTIFS('V 1.9 TEST'!$A$2:$A$1000,"N/A",'V 1.9 TEST'!$B$2:$B$1000,"<>") -> 0 | F12: Primary browser / version
B13: Executed (Pass + Fail) | C13: =SUM(C7:C8) -> 0 | F13: Secondary browser / device
B14: Execution coverage | C14: =IF(C6-C12=0,0,C13/(C6-C12)) -> 0 | F14: Functional review decision | G14: Not reviewed
B15: Pass rate of executed | C15: =IF(C13=0,"n.a.",C7/C13) -> n.a.
B16: Unrecognized / blank status | C16: =C6-SUM(C7:C12) -> 0
B18: Functional completion | F18: Run order
B19: Applicable functional cases | C19: =COUNTIFS('V 1.9 TEST'!$B$2:$B$1000,"<>",'V 1.9 TEST'!$J$2:$J$1000,"<>Visual",'V 1.9 TEST'!$A$2:$A$1000,"<>N/A") -> 629 | F19: 1. Prepare | G19: Enter URL/build, accounts and effective flags. Do not copy passwords or tokens into this workbook.
B20: Functional Pass | C20: =COUNTIFS('V 1.9 TEST'!$B$2:$B$1000,"<>",'V 1.9 TEST'!$J$2:$J$1000,"<>Visual",'V 1.9 TEST'!$A$2:$A$1000,"Pass") -> 0 | F20: 2. Smoke | G20: Filter Run Set = Smoke. Run the critical end-to-end journeys first.
B21: Functional checks remaining | C21: =C19-C20 -> 629 | F21: 3. Regression | G21: Run current in-scope regression cases by suite and persona. Then run Extended integration checks.
B22: P0 Fail / Blocked / Retest | C22: =COUNTIFS('V 1.9 TEST'!$G$2:$G$1000,"P0",'V 1.9 TEST'!$A$2:$A$1000,"Fail")+COUNTIFS('V 1.9 TEST'!$G$2:$G$1000,"P0",'V 1.9 TEST'!$A$2:$A$1000,"Blocked")+COUNTIFS('V 1.9 TEST'!$G$2:$G$1000,"P0",'V 1.9 TEST'!$A$2:$A$1000,"Retest") -> 0 | F22: 4. Record | G22: Use Status, Actual Result, Notes, Evidence Link, date, tester, browser/viewport and Issue Link.
B23: Run state | C23: =IF(OR(G7="",G8=""),"Record URL and build",IF(C16<>0,"Check status entries",IF(C21>0,"Testing incomplete",IF(G14<>"Approved","Review required","Functional review approved")))) -> Record URL and build | F23: 5. Retest | G23: Filter Previous Status for Retest, Fail or Blocked. Historical status is context and never a current pass.
F24: 6. Visual | G24: Capture current appearance, accessibility and motion after functionality. Log later cosmetic work in UX Backlog.
B27: Coverage by suite
B28: Suite | C28: Total | D28: Pass | F28: Fail | G28: Blocked | H28: Remaining
B29: Public Website | C29: =COUNTIFS('V 1.9 TEST'!$C$2:$C$1000,B29) -> 10 | D29: =COUNTIFS('V 1.9 TEST'!$C$2:$C$1000,B29,'V 1.9 TEST'!$A$2:$A$1000,"Pass") -> 0 | F29: =COUNTIFS('V 1.9 TEST'!$C$2:$C$1000,B29,'V 1.9 TEST'!$A$2:$A$1000,"Fail") -> 0 | G29: =COUNTIFS('V 1.9 TEST'!$C$2:$C$1000,B29,'V 1.9 TEST'!$A$2:$A$1000,"Blocked") -> 0 | H29: =C29-D29-COUNTIFS('V 1.9 TEST'!$C$2:$C$1000,B29,'V 1.9 TEST'!$A$2:$A$1000,"N/A") -> 10
B30: Auth | C30: =COUNTIFS('V 1.9 TEST'!$C$2:$C$1000,B30) -> 7 | D30: =COUNTIFS('V 1.9 TEST'!$C$2:$C$1000,B30,'V 1.9 TEST'!$A$2:$A$1000,"Pass") -> 0 | F30: =COUNTIFS('V 1.9 TEST'!$C$2:$C$1000,B30,'V 1.9 TEST'!$A$2:$A$1000,"Fail") -> 0 | G30: =COUNTIFS('V 1.9 TEST'!$C$2:$C$1000,B30,'V 1.9 TEST'!$A$2:$A$1000,"Blocked") -> 0 | H30: =C30-D30-COUNTIFS('V 1.9 TEST'!$C$2:$C$1000,B30,'V 1.9 TEST'!$A$2:$A$1000,"N/A") -> 7
B31: Onboarding | C31: =COUNTIFS('V 1.9 TEST'!$C$2:$C$1000,B31) -> 5 | D31: =COUNTIFS('V 1.9 TEST'!$C$2:$C$1000,B31,'V 1.9 TEST'!$A$2:$A$1000,"Pass") -> 0 | F31: =COUNTIFS('V 1.9 TEST'!$C$2:$C$1000,B31,'V 1.9 TEST'!$A$2:$A$1000,"Fail") -> 0 | G31: =COUNTIFS('V 1.9 TEST'!$C$2:$C$1000,B31,'V 1.9 TEST'!$A$2:$A$1000,"Blocked") -> 0 | H31: =C31-D31-COUNTIFS('V 1.9 TEST'!$C$2:$C$1000,B31,'V 1.9 TEST'!$A$2:$A$1000,"N/A") -> 5
B32: Profile | C32: =COUNTIFS('V 1.9 TEST'!$C$2:$C$1000,B32) -> 4 | D32: =COUNTIFS('V 1.9 TEST'!$C$2:$C$1000,B32,'V 1.9 TEST'!$A$2:$A$1000,"Pass") -> 0 | F32: =COUNTIFS('V 1.9 TEST'!$C$2:$C$1000,B32,'V 1.9 TEST'!$A$2:$A$1000,"Fail") -> 0 | G32: =COUNTIFS('V 1.9 TEST'!$C$2:$C$1000,B32,'V 1.9 TEST'!$A$2:$A$1000,"Blocked") -> 0 | H32: =C32-D32-COUNTIFS('V 1.9 TEST'!$C$2:$C$1000,B32,'V 1.9 TEST'!$A$2:$A$1000,"N/A") -> 4
B33: CV | C33: =COUNTIFS('V 1.9 TEST'!$C$2:$C$1000,B33) -> 6 | D33: =COUNTIFS('V 1.9 TEST'!$C$2:$C$1000,B33,'V 1.9 TEST'!$A$2:$A$1000,"Pass") -> 0 | F33: =COUNTIFS('V 1.9 TEST'!$C$2:$C$1000,B33,'V 1.9 TEST'!$A$2:$A$1000,"Fail") -> 0 | G33: =COUNTIFS('V 1.9 TEST'!$C$2:$C$1000,B33,'V 1.9 TEST'!$A$2:$A$1000,"Blocked") -> 0 | H33: =C33-D33-COUNTIFS('V 1.9 TEST'!$C$2:$C$1000,B33,'V 1.9 TEST'!$A$2:$A$1000,"N/A") -> 6
B34: Projects | C34: =COUNTIFS('V 1.9 TEST'!$C$2:$C$1000,B34) -> 17 | D34: =COUNTIFS('V 1.9 TEST'!$C$2:$C$1000,B34,'V 1.9 TEST'!$A$2:$A$1000,"Pass") -> 0 | F34: =COUNTIFS('V 1.9 TEST'!$C$2:$C$1000,B34,'V 1.9 TEST'!$A$2:$A$1000,"Fail") -> 0 | G34: =COUNTIFS('V 1.9 TEST'!$C$2:$C$1000,B34,'V 1.9 TEST'!$A$2:$A$1000,"Blocked") -> 0 | H34: =C34-D34-COUNTIFS('V 1.9 TEST'!$C$2:$C$1000,B34,'V 1.9 TEST'!$A$2:$A$1000,"N/A") -> 17
B35: Applications | C35: =COUNTIFS('V 1.9 TEST'!$C$2:$C$1000,B35) -> 11 | D35: =COUNTIFS('V 1.9 TEST'!$C$2:$C$1000,B35,'V 1.9 TEST'!$A$2:$A$1000,"Pass") -> 0 | F35: =COUNTIFS('V 1.9 TEST'!$C$2:$C$1000,B35,'V 1.9 TEST'!$A$2:$A$1000,"Fail") -> 0 | G35: =COUNTIFS('V 1.9 TEST'!$C$2:$C$1000,B35,'V 1.9 TEST'!$A$2:$A$1000,"Blocked") -> 0 | H35: =C35-D35-COUNTIFS('V 1.9 TEST'!$C$2:$C$1000,B35,'V 1.9 TEST'!$A$2:$A$1000,"N/A") -> 11
B36: Admin | C36: =COUNTIFS('V 1.9 TEST'!$C$2:$C$1000,B36) -> 6 | D36: =COUNTIFS('V 1.9 TEST'!$C$2:$C$1000,B36,'V 1.9 TEST'!$A$2:$A$1000,"Pass") -> 0 | F36: =COUNTIFS('V 1.9 TEST'!$C$2:$C$1000,B36,'V 1.9 TEST'!$A$2:$A$1000,"Fail") -> 0 | G36: =COUNTIFS('V 1.9 TEST'!$C$2:$C$1000,B36,'V 1.9 TEST'!$A$2:$A$1000,"Blocked") -> 0 | H36: =C36-D36-COUNTIFS('V 1.9 TEST'!$C$2:$C$1000,B36,'V 1.9 TEST'!$A$2:$A$1000,"N/A") -> 6
B37: Billing | C37: =COUNTIFS('V 1.9 TEST'!$C$2:$C$1000,B37) -> 17 | D37: =COUNTIFS('V 1.9 TEST'!$C$2:$C$1000,B37,'V 1.9 TEST'!$A$2:$A$1000,"Pass") -> 0 | F37: =COUNTIFS('V 1.9 TEST'!$C$2:$C$1000,B37,'V 1.9 TEST'!$A$2:$A$1000,"Fail") -> 0 | G37: =COUNTIFS('V 1.9 TEST'!$C$2:$C$1000,B37,'V 1.9 TEST'!$A$2:$A$1000,"Blocked") -> 0 | H37: =C37-D37-COUNTIFS('V 1.9 TEST'!$C$2:$C$1000,B37,'V 1.9 TEST'!$A$2:$A$1000,"N/A") -> 17
B38: Firestore Rules | C38: =COUNTIFS('V 1.9 TEST'!$C$2:$C$1000,B38) -> 7 | D38: =COUNTIFS('V 1.9 TEST'!$C$2:$C$1000,B38,'V 1.9 TEST'!$A$2:$A$1000,"Pass") -> 0 | F38: =COUNTIFS('V 1.9 TEST'!$C$2:$C$1000,B38,'V 1.9 TEST'!$A$2:$A$1000,"Fail") -> 0 | G38: =COUNTIFS('V 1.9 TEST'!$C$2:$C$1000,B38,'V 1.9 TEST'!$A$2:$A$1000,"Blocked") -> 0 | H38: =C38-D38-COUNTIFS('V 1.9 TEST'!$C$2:$C$1000,B38,'V 1.9 TEST'!$A$2:$A$1000,"N/A") -> 7
B39: UX | C39: =COUNTIFS('V 1.9 TEST'!$C$2:$C$1000,B39) -> 8 | D39: =COUNTIFS('V 1.9 TEST'!$C$2:$C$1000,B39,'V 1.9 TEST'!$A$2:$A$1000,"Pass") -> 0 | F39: =COUNTIFS('V 1.9 TEST'!$C$2:$C$1000,B39,'V 1.9 TEST'!$A$2:$A$1000,"Fail") -> 0 | G39: =COUNTIFS('V 1.9 TEST'!$C$2:$C$1000,B39,'V 1.9 TEST'!$A$2:$A$1000,"Blocked") -> 0 | H39: =C39-D39-COUNTIFS('V 1.9 TEST'!$C$2:$C$1000,B39,'V 1.9 TEST'!$A$2:$A$1000,"N/A") -> 8
B40: Release | C40: =COUNTIFS('V 1.9 TEST'!$C$2:$C$1000,B40) -> 2 | D40: =COUNTIFS('V 1.9 TEST'!$C$2:$C$1000,B40,'V 1.9 TEST'!$A$2:$A$1000,"Pass") -> 0 | F40: =COUNTIFS('V 1.9 TEST'!$C$2:$C$1000,B40,'V 1.9 TEST'!$A$2:$A$1000,"Fail") -> 0 | G40: =COUNTIFS('V 1.9 TEST'!$C$2:$C$1000,B40,'V 1.9 TEST'!$A$2:$A$1000,"Blocked") -> 0 | H40: =C40-D40-COUNTIFS('V 1.9 TEST'!$C$2:$C$1000,B40,'V 1.9 TEST'!$A$2:$A$1000,"N/A") -> 2
... B70: Baseline & Recovery | C70: =COUNTIFS('V 1.9 TEST'!$C$2:$C$1000,B70) -> 5 | D70: =COUNTIFS('V 1.9 TEST'!$C$2:$C$1000,B70,'V 1.9 TEST'!$A$2:$A$1000,"Pass") -> 0 | F70: =COUNTIFS('V 1.9 TEST'!$C$2:$C$1000,B70,'V 1.9 TEST'!$A$2:$A$1000,"Fail") -> 0 | G70: =COUNTIFS('V 1.9 TEST'!$C$2:$C$1000,B70,'V 1.9 TEST'!$A$2:$A$1000,"Blocked") -> 0 | H70: =C70-D70-COUNTIFS('V 1.9 TEST'!$C$2:$C$1000,B70,'V 1.9 TEST'!$A$2:$A$1000,"N/A") -> 5
B73: Run conventions
B74: Statuses | C74: Not Run: untouched. Pass: observed expected result. Fail: observed defect. Blocked: prerequisite unavailable. Retest: fix awaits verification. N/A: deliberately outside this run; explain why in Notes.
B75: Priorities | C75: P0: critical flow, privacy, entitlement or data integrity. P1: normal functional behavior. P2: lower-impact presentation or refinement. These priorities order this test run.
B76: Scope | C76: Record actual flags below. Enabled but unusable because data, credentials or an index is missing = Blocked. Intentionally disabled/out-of-scope = N/A with a reason. Exercise disabled-state checks as well.
B77: Coverage calculation | C77: Execution coverage = (Pass + Fail) / (all cases minus N/A). Retest and Blocked are unresolved. Pass rate = Pass / (Pass + Fail). Visual cases are excluded from functional completion only.
B78: Browser coverage | C78: Run smoke on current Chromium desktop and a real mobile browser. Repeat primary forms/navigation in Firefox or Safari/Edge. Record actual versions and viewport. Use 390×844, 768×1024 and 1440×900 as layout checkpoints.
B79: Account fixtures | C79: Use Accounts for existing identities. Add controlled Mentor verified/unverified, second matching member, expired member, invited learner and instructor as needed. Prepare states; do not grant rights to real users for testing.
B80: Test data | C80: Use QA prefixes and synthetic projects, packs, cohorts, votes and addresses. Use controlled inboxes and sandbox billing. Record created IDs for cleanup. Time-bound cases need prepared records or a controlled QA clock.
B81: Evidence | C81: For a failure record steps taken, observed versus expected result, URL/build, account persona, browser/viewport and screenshot/video or network error. Remove secrets and private customer data from evidence.
B82: Before cosmetic work | C82: Resolve or explicitly triage critical functional/access/privacy failures. Finish the functional checks and review. Use visual evidence as a baseline for later UI, motion and cosmetic work.
B83: History | C83: All eight original tabs are retained. This new run starts Not Run throughout. Previous Status and Previous Notes carry context only. Earlier developer claims in Known Issues are not fresh manual results.
B84: Product decisions | C84: Known Issues #5, #15, #24, #34, #40, #44 and #46 include requests or unresolved decisions. They are not instructions to implement features. Test present behavior and log follow-ups separately.
B87: Effective feature flags for this tested deployment
B88: GO_MATCHMAKING_ENABLED | D88: Unverified | F88: Production default on. Preview default off.
B89: GO_DEVELOPMENT_JOURNEY_ENABLED | D89: Unverified | F89: Default off. Test enabled and disabled behavior in QA.
B90: GO_GAME_JAMS_ENABLED | D90: Unverified | F90: Default off. Separate RSVP from verified attendance.
B91: COURSE_ENROLLMENT_ENABLED | D91: Unverified | F91: Default off. Enrollment requires effective enablement.
B92: VIDEO_BUNDLES_ENABLED | D92: Unverified | F92: Default off.
B93: USER_NOTIFICATIONS_ENABLED | D93: Unverified | F93: Default off.
B94: MENTOR_DIRECTORY_ENABLED | D94: Unverified | F94: Normally enabled at runtime.
B95: MENTOR_AVAILABILITY_ENABLED | D95: Unverified | F95: Normally enabled at runtime.
B96: MENTOR_CHECKOUT_ENABLED | D96: Unverified | F96: Default on. Purchase does not verify mentor.
B97: COMMUNITY_ASSET_SUBMISSIONS_ENABLED | D97: Unverified | F97: Default follows production runtime.
B98: MENTORSHIP_SYSTEM_ENABLED / REQUESTS | D98: Unverified | F98: Default on. Record overrides and application setting.
B99: NEWSLETTER_ENABLED | D99: Unverified | F99: Record actual environment setting.
B102: Coverage reference
B103: Baseline | C103: Website Test Suite (2).xlsx. V 1.8 TEST contains 528 cases. Prior test rounds and Known Issues are retained in their original tabs.
B104: Reviewed code | C104: Repository commit 5e7a261, 27 October 2026. Local committed implementation reviewed on 28 October 2026. Actual tested deployment/build must be entered separately.
B105: Membership and projects | C105: src/constants/membership.js, src/lib/go-policy.js, src/lib/project-capacity.js. Free Passport. Community/Mentor one unreleased own-game slot. Business agreed capacity. Mentor interview is separate from purchase.
B106: Feature availability | C106: src/lib/product-config.js, commit a8580c9. Team matchmaking defaults on for production, off for previews. Journey/jams and several product features are gated. Effective deployment overrides are not verified.
B107: Learning | C107: docs/STARTER_PATHWAY_RELEASE.md, docs/IDEA_TO_PLAYABLE_RELEASE.md. Current course placement, private evidence, XP, cohorts, physical-seat policy, human assessment and recording access.
B108: Community | C108: docs/MONDAY_BUILDS_AND_PASSPORT_STAMPS.md, src/lib/go-journey-service.js. Weekly voting, official awards, explicit matching opt-in and privacy.
B109: Merch | C109: src/lib/merch-core.js, src/lib/merch-server.js, docs/RELEASE-HANDOFF-2026-10-23.md. Reservations, independent duo selection, confirmation, retry, fulfillment and retention. The later flag code overrides older handoff defaults.
B110: Mentorship and support | C110: src/lib/mentorship.js, src/components/mentors/MentorshipRequestWorkspace.jsx, src/lib/support-tickets.js. Staff review before forwarding, agreement lifecycle, private support and role checks.

Sheet V 1.9 TEST
A1: Status | B1: Test ID | C1: Suite | D1: Steps | E1: Expected Result | F1: Feature | G1: Priority | H1: Persona | I1: Preconditions | J1: Run Set | K1: Actual Result | L1: Notes | M1: Evidence Link | N1: Run Date | O1: Tester | P1: Browser / Viewport | Q1: Issue Link | R1: Scope / Feature Flag | S1: Previous Status | T1: Previous Notes / Source | U1: Change
A2: Not Run | B2: GO-MAN-001 | C2: Public Website | D2: Open the home page; wait for the page to fully load; check above-the-fold content; scroll to bottom | E2: Home page loads without console-visible broken UI; main brand/content is clear; no missing critical images; footer is reachable | F2: Home page load | G2: P0 | H2: Visitor | I2: Production or local site is running | J2: Smoke | R2: Core | S2: Not Run | T2: V 1.7 TEST: Functionally clean, however there are multiple improvements to be made on the Landing Page Bugs will be reported | U2: Retained
A3: Not Run | B3: GO-MAN-002 | C3: Public Website | D3: Open home page; click each main nav item; use browser back; repeat for logo/home link | E3: Every nav item routes to the expected page; no 404; active page content matches navigation label | F3: Desktop navigation | G3: P0 | H3: Visitor | I3: Site is running on desktop viewport | J3: Smoke | R3: Core | S3: Not Run | U3: Retained
A4: Not Run | B4: GO-MAN-003 | C4: Public Website | D4: Resize to mobile or use phone; open mobile menu; tap every nav item; close and reopen menu | E4: Mobile menu is usable; links work; menu does not overlap content; menu can be dismissed | F4: Mobile navigation | G4: P0 | H4: Visitor | I4: Site is running on mobile viewport | J4: Smoke | R4: Core | S4: Not Run | U4: Retained
A5: Not Run | B5: GO-MAN-004 | C5: Public Website | D5: Open home page; click primary CTA; return; click secondary CTAs; check destination pages | E5: CTAs route to intended signup/pricing/contact/project pages; labels match destination intent | F5: Landing CTAs | G5: P0 | H5: Visitor | I5: Site is running | J5: Regression | R5: Core | S5: Not Run | U5: Retained
A6: Not Run | B6: GO-MAN-005 | C6: Public Website | D6: Check home/pricing/projects/about/FAQ pages at 390px 768px and desktop widths | E6: No horizontal scrolling; text does not overlap; buttons fit; sections remain readable | F6: Responsive layout | G6: P1 | H6: Visitor | I6: Use desktop tablet and mobile widths | J6: Regression | R6: Core | S6: Not Run | U6: Retained
A7: Not Run | B7: GO-MAN-006 | C7: Public Website | D7: Open key public pages; look for broken images/icons; refresh once | E7: Images/icons render correctly; no obvious layout jumps due to missing assets | F7: Image and asset loading | G7: P1 | H7: Visitor | I7: Site is running | J7: Regression | R7: Core | S7: Not Run | U7: Retained
A8: Not Run | B8: GO-MAN-007 | C8: Public Website | D8: Open FAQ; expand/collapse each FAQ item; check links if present | E8: FAQ controls work; content is readable; links open expected destinations | F8: FAQ page | G8: P1 | H8: Visitor | I8: FAQ page exists | J8: Regression | R8: Core | S8: Retest | T8: V 1.7 TEST: Functionality is there but test is failed but the information is innacurate, we need to update the FAQ to reflect the real business proposition we are offering | U8: Retained
A9: Not Run | B9: GO-MAN-008 | C9: Public Website | D9: Open About; scan page content; test visible links/buttons | E9: About content is readable and current; links/buttons work; no typo-heavy or placeholder content | F9: About page | G9: P1 | H9: Visitor | I9: About page exists | J9: Regression | R9: Core | S9: Retest | T9: V 1.7 TEST: Functionality is there but test is failed but the information is innacurate, we need to update the ABOIT US to reflect the real business proposition we are offering | U9: Retained
A10: Not Run | B10: GO-MAN-009 | C10: Public Website | D10: Open pricing page; inspect all tiers and intervals; toggle monthly/annual if available | E10: Pricing is understandable; member vs company benefits are clear; checkout buttons are visible | F10: Pricing page | G10: P0 | H10: Visitor | I10: Polar products configured | J10: Smoke | R10: Core | S10: Not Run | T10: V 1.7 TEST: We offer a community newsletter but we don't have one. See what we need in order to have one. | U10: Retained
A11: Not Run | B11: GO-MAN-010 | C11: Public Website | D11: Open a nonsense URL such as /this-page-does-not-exist | E11: User sees a graceful not-found or redirect experience; no raw error stack | F11: 404/not-found experience | G11: P2 | H11: Visitor | I11: Site is running | J11: Regression | R11: Core | S11: Not Run | U11: Retained
A12: Not Run | B12: GO-MAN-011 | C12: Auth | D12: Open signup; create account; complete required fields; submit | E12: Account is created; user lands on expected next page; no duplicate or confusing messages | F12: Signup flow | G12: P0 | H12: Visitor | I12: Test email available | J12: Smoke | R12: Core | S12: Not Run | U12: Retained
A13: Not Run | B13: GO-MAN-012 | C13: Auth | D13: Open login; enter valid credentials; submit | E13: User logs in; protected nav/profile state appears; no unexpected redirect loop | F13: Login flow | G13: P0 | H13: Free User | I13: Existing account available | J13: Smoke | R13: Core | S13: Not Run | U13: Retained
A14: Not Run | B14: GO-MAN-013 | C14: Auth | D14: Enter invalid credentials; submit | E14: Clear error appears; password is not exposed; form remains usable | F14: Invalid login | G14: P1 | H14: Visitor | I14: Login page available | J14: Regression | R14: Core | S14: Not Run | U14: Retained
A15: Not Run | B15: GO-MAN-014 | C15: Auth | D15: Use profile/menu logout action; confirm logged-out state | E15: Session ends; protected links redirect or hide; public pages still work | F15: Logout flow | G15: P0 | H15: Logged-in User | I15: User is logged in | J15: Smoke | R15: Core | S15: Not Run | U15: Retained
A16: Not Run | B16: GO-MAN-015 | C16: Auth | D16: Open reset password; enter test account email; submit | E16: User receives success state; reset email is sent if email service is configured | F16: Password reset | G16: P1 | H16: Visitor | I16: Reset password page and email service configured | J16: Regression | R16: Core | S16: Retest | T16: V 1.7 TEST: Reset password throrws error Failed to send reset email. Please try again | U16: Retained
A17: Not Run | B17: GO-MAN-016 | C17: Auth | D17: Open /dashboard /billing /admin /project/create directly | E17: Logged-out visitor is redirected or shown auth-required state; no protected data is visible | F17: Protected route redirect | G17: P0 | H17: Visitor | I17: Logged out | J17: Smoke | R17: Core | S17: Not Run | U17: Retained
A18: Not Run | B18: GO-MAN-017 | C18: Auth | D18: Refresh current page; close and reopen browser tab; revisit site | E18: Session remains valid if expected; user identity and nav state are stable | F18: Session persistence | G18: P1 | H18: Logged-in User | I18: User is logged in | J18: Regression | R18: Core | S18: Not Run | U18: Retained
A19: Not Run | B19: GO-MAN-018 | C19: Onboarding | D19: Open onboarding page; begin onboarding flow | E19: Onboarding starts cleanly; first step is clear; progress is visible if expected | F19: Start onboarding | G19: P0 | H19: Logged-in User | I19: Logged in as member | J19: Regression | R19: Core | S19: Not Run | U19: Retained
A20: Not Run | B20: GO-MAN-019 | C20: Onboarding | D20: Complete every required onboarding step with valid values; submit final step | E20: Profile is saved; completion state appears; user can proceed to CV generation | F20: Complete required fields | G20: P0 | H20: Logged-in User | I20: Onboarding available | J20: Smoke | R20: Core | S20: Not Run | U20: Retained
A21: Not Run | B21: GO-MAN-020 | C21: Onboarding | D21: Leave required fields empty; enter invalid URLs; exceed long text limits; submit | E21: Helpful validation errors appear; entered valid data is preserved; user can correct and continue | F21: Validation errors | G21: P1 | H21: Logged-in User | I21: Onboarding available | J21: Regression | R21: Core | S21: Not Run | U21: Retained
A22: Not Run | B22: GO-MAN-021 | C22: Onboarding | D22: Move forward several steps; go back; edit previous values; move forward again | E22: Previously entered values persist; progress remains correct; no data loss | F22: Back/forward navigation | G22: P1 | H22: Logged-in User | I22: Onboarding in progress | J22: Regression | R22: Core | S22: Not Run | U22: Retained
A23: Not Run | B23: GO-MAN-022 | C23: Onboarding | D23: Complete onboarding on mobile viewport | E23: Controls are tappable; inputs fit screen; progress and buttons remain visible | F23: Mobile onboarding | G23: P1 | H23: Logged-in User | I23: Mobile viewport | J23: Regression | R23: Core | S23: Not Run | U23: Retained
A24: Not Run | B24: GO-MAN-023 | C24: Profile | D24: Open profile page; inspect displayed fields | E24: Profile displays current user data; no private admin-only fields are shown | F24: View own profile | G24: P0 | H24: Logged-in User | I24: Profile data exists | J24: Regression | R24: Core | S24: Not Run | U24: Retained
A25: Not Run | B25: GO-MAN-024 | C25: Profile | D25: Edit display name role tools portfolio links and visibility settings; save | E25: Changes save successfully and persist after refresh | F25: Edit profile | G25: P0 | H25: Logged-in User | I25: Profile page available | J25: Smoke | R25: Core | S25: Not Run | U25: Retained
A26: Not Run | B26: GO-MAN-025 | C26: Profile | D26: Enter social/portfolio URL without http/https; save | E26: Validation error appears; invalid URL is not silently accepted | F26: Profile invalid social URL | G26: P1 | H26: Logged-in User | I26: Profile editor available | J26: Regression | R26: Core | S26: Not Run | U26: Retained
A27: Not Run | B27: GO-MAN-026 | C27: Profile | D27: Toggle public/private or visibility settings; save; view from another account if possible | E27: Visibility settings persist and affect what other users can see | F27: Privacy settings | G27: P1 | H27: Logged-in User | I27: Profile editor available | J27: Regression | R27: Core | S27: Not Run | U27: Retained
A28: Not Run | B28: GO-MAN-027 | C28: CV | D28: Open CV page; click generate; wait for result | E28: CV is generated from profile data; title summary sections appear; no invented facts are obvious | F28: Generate CV | G28: P0 | H28: Logged-in User | I28: Onboarding profile completed | J28: Smoke | R28: Core | S28: Not Run | U28: Retained
A29: Not Run | B29: GO-MAN-028 | C29: CV | D29: Generate a Passport from a completed onboarding profile without any AI service configured. Refresh it. | E29: Generation succeeds using stored profile facts. No AI key or AI consent is required. | F29: Passport generation without AI | G29: P1 | H29: Logged-in User | I29: AI key disabled or unavailable in test env | J29: Regression | R29: Core | S29: Retest | T29: V 1.7 TEST: We will not be using AI for creation and updates of CV at the moment maybe in the future, all mentions for AI being used or consent formes need to be removed. | U29: Updated
A30: Not Run | B30: GO-MAN-029 | C30: CV | D30: Edit CV title summary and at least one section; save | E30: Edits persist after refresh; formatting remains readable | F30: Edit CV | G30: P0 | H30: Logged-in User | I30: CV exists | J30: Regression | R30: Core | S30: Not Run | U30: Retained
A31: Not Run | B31: GO-MAN-030 | C31: CV | D31: Click publish/approve; confirm if prompted | E31: CV status becomes active/published; user receives clear success state | F31: Publish CV | G31: P0 | H31: Logged-in User | I31: Draft CV exists | J31: Smoke | R31: Core | S31: Not Run | U31: Retained
A32: Not Run | B32: GO-MAN-031 | C32: CV | D32: Change CV visibility settings; view user/project application context from another account | E32: CV is visible only where expected based on settings | F32: CV visibility | G32: P1 | H32: Logged-in User | I32: CV exists and second account available | J32: Regression | R32: Core | S32: Not Run | U32: Retained
A33: Not Run | B33: GO-MAN-032 | C33: CV | D33: Open CV page; edit and publish on mobile | E33: CV editor and publish controls are usable; no clipped text/buttons | F33: CV mobile usability | G33: P1 | H33: Logged-in User | I33: Mobile viewport | J33: Regression | R33: Core | S33: Not Run | U33: Retained
A34: Not Run | B34: GO-MAN-033 | C34: Projects | D34: Open /projects while logged out; inspect visible projects | E34: Visitor sees only public discoverable projects; no private/draft/pending projects appear | F34: Project listing visitor | G34: P0 | H34: Visitor | I34: Projects exist with different statuses/visibility | J34: Smoke | R34: Core | S34: Not Run | U34: Retained
A35: Not Run | B35: GO-MAN-034 | C35: Projects | D35: Open a public project detail page | E35: Project detail loads; visible fields are appropriate for visitor; apply controls require login/membership | F35: Project detail visitor | G35: P0 | H35: Visitor | I35: Public hiring/live/completed project exists | J35: Regression | R35: Core | S35: Not Run | U35: Retained
A36: Not Run | B36: GO-MAN-035 | C36: Projects | D36: Open private project URL as visitor/unrelated account | E36: Access is denied or redirected; private details are not visible | F36: Private project access | G36: P0 | H36: Visitor or unrelated user | I36: Private project exists | J36: Smoke | R36: Core | S36: Not Run | U36: Retained
A37: Not Run | B37: GO-MAN-036 | C37: Projects | D37: As a free user, open /project/create and choose the creator path. | E37: Membership guidance appears. No project is created. | F37: Free user creator-project gate | G37: P0 | H37: Free User | I37: Logged in without active company membership | J37: Regression | R37: Core | S37: Not Run | U37: Updated
A38: Not Run | B38: GO-MAN-037 | C38: Projects | D38: As an active Community member with no occupied slot, open /project/create, choose your own game, complete the wizard and submit. | E38: One draft creator project is saved. The member is not forced to buy Business for this path. | F38: Community creator-project allowance | G38: P0 | H38: Active Community member | I38: Use prepared QA records and separate accounts. Record the actual URL and build on Run Overview. No unreleased project in the capacity ledger. | J38: Smoke | R38: Core | S38: Not Run | U38: Updated
A39: Not Run | B39: GO-MAN-038 | C39: Projects | D39: As Business with agreed unused capacity, create a project and select a new source project. Refresh the creator workspace. | E39: One draft and one linked source record exist. Owner and team references are correct. | F39: Business creates project with new source | G39: P0 | H39: Company Subscriber | I39: Use prepared QA records and separate accounts. Record the actual URL and build on Run Overview. Business account has a positive agreed project limit. | J39: Smoke | R39: Core | S39: Retest | T39: V 1.7 TEST: I should not be able to select source projects from other projects that I am not the owner of or I haven't created as a company subscriber. I also as a company subscriber should be able to see the projects I have created as drafts under my projects and allow me to edit them even though they are only in draft and not approved by the admin. I also managed to create duplicates projects somehow, the project i created is called TEST 5 maybe you can use some info in the way it was created to help you or I will try to catch .har file. | U39: Updated
A40: Not Run | B40: GO-MAN-039 | C40: Projects | D40: As Business with an owned source and spare capacity, create a second project linked to that source. | E40: The saved project links to the chosen source. Another creator’s source cannot be selected. | F40: Business creates project with owned source | G40: P1 | H40: Company Subscriber | I40: Use prepared QA records and separate accounts. Record the actual URL and build on Run Overview. Business account has unused agreed capacity and an owned source. | J40: Regression | R40: Core | S40: Not Run | U40: Updated
A41: Not Run | B41: GO-MAN-040 | C41: Projects | D41: Submit empty form; enter invalid budget duration role visibility/type values | E41: Clear field errors appear; invalid project is not created | F41: Project form validation | G41: P0 | H41: Company Subscriber | I41: Project create form available | J41: Regression | R41: Core | S41: Not Run | U41: Retained
A42: Not Run | B42: GO-MAN-041 | C42: Projects | D42: Open project edit page; change title description budget duration roles; save | E42: Changes save and persist; owner remains authorized | F42: Owner edit draft | G42: P0 | H42: Project Owner | I42: Draft project exists | J42: Smoke | R42: Core | S42: Not Run | U42: Retained
A43: Not Run | B43: GO-MAN-042 | C43: Projects | D43: Attempt to change status to hiring/live/completed/rejected as non-admin owner | E43: Owner is blocked from admin-only status transitions | F43: Owner status restriction | G43: P0 | H43: Project Owner | I43: Draft project exists | J43: Regression | R43: Core | S43: Retest | T43: V 1.7 TEST: Users can update their project status. This must be stopped because it creates issues with admin, creator users can only observe the current status of their project and you can suggest to contact support if they want an update on their project. | U43: Retained
A44: Not Run | B44: GO-MAN-043 | C44: Projects | D44: Open admin/project edit; set status to hiring; save | E44: Project becomes public/discoverable according to visibility and status | F44: Admin publish project | G44: P0 | H44: Platform Admin | I44: Draft/pending project exists | J44: Smoke | R44: Core | S44: Not Run | U44: Retained
A45: Not Run | B45: GO-MAN-044 | C45: Projects | D45: Set project status to rejected; save; check discovery | E45: Rejected project is hidden from public discovery; owner/admin can still inspect as intended | F45: Admin reject project | G45: P1 | H45: Platform Admin | I45: Project exists | J45: Regression | R45: Core | S45: Retest | T45: V 1.7 TEST: Owner cannot inspect it and it doesn't show in /myprojets it only can be seen in admin and can be updated to a different status. | U45: Retained
A46: Not Run | B46: GO-MAN-045 | C46: Projects | D46: Archive project; refresh projects list; open direct URL as owner and unrelated user | E46: Archived project disappears from discovery; owner/admin can access; unrelated user cannot | F46: Archive project | G46: P1 | H46: Project Owner or Admin | I46: Project exists | J46: Regression | R46: Core | S46: Not Run | U46: Retained
A47: Not Run | B47: GO-MAN-046 | C47: Projects | D47: Restore/unarchive project if UI supports it; refresh list | E47: Project visibility returns according to status/visibility rules | F47: Restore project | G47: P1 | H47: Project Owner or Admin | I47: Archived project exists | J47: Regression | R47: Core | S47: Not Run | U47: Retained
A48: Not Run | B48: GO-MAN-047 | C48: Projects | D48: Delete project; confirm; check project list and direct URL | E48: Project is removed; direct URL no longer loads; related applications are removed or inaccessible | F48: Delete own project | G48: P0 | H48: Project Owner | I48: Owner project exists | J48: Smoke | R48: Core | S48: Not Run | U48: Retained
A49: Not Run | B49: GO-MAN-048 | C49: Projects | D49: Delete another user's project as admin; confirm | E49: Admin can delete; project disappears; owner no longer sees it | F49: Admin delete any project | G49: P0 | H49: Platform Admin | I49: Project owned by another user exists | J49: Regression | R49: Core | S49: Retest | T49: V 1.7 TEST: The admin user cannot delete a project, only archive it | U49: Retained
A50: Not Run | B50: GO-MAN-049 | C50: Projects | D50: Attempt delete/edit project via UI/direct URL | E50: Access is denied; no project data changes | F50: Non-owner delete block | G50: P0 | H50: Unrelated User | I50: Project owned by another user exists | J50: Regression | R50: Core | S50: Not Run | U50: Retained
A51: Not Run | B51: GO-MAN-050 | C51: Applications | D51: Open hiring project; click apply; attempt application | E51: Free user is blocked with clear membership requirement | F51: Apply requires membership | G51: P0 | H51: Free User | I51: Public hiring project exists | J51: Smoke | R51: Core | S51: Not Run | U51: Retained
A52: Not Run | B52: GO-MAN-051 | C52: Applications | D52: Open project; apply with role motivation availability | E52: Application is created as pending; user sees success; project owner can see it | F52: Member apply to hiring project | G52: P0 | H52: Member Subscriber | I52: Public hiring project exists and active CV exists | J52: Smoke | R52: Core | S52: Not Run | U52: Retained
A53: Not Run | B53: GO-MAN-052 | C53: Applications | D53: Apply to project; edit CV afterwards; inspect application as project owner/admin | E53: Application retains original CV snapshot; later CV edits do not alter historical application | F53: CV snapshot on apply | G53: P0 | H53: Member Subscriber | I53: CV exists and project accepts applications | J53: Smoke | R53: Core | S53: Retest | T53: V 1.7 TEST: I want the creator to be able to see the moment the user applied and the current user profile as well two different links, the functionality is good as it is, but I also want creators to be able to observe public profiles with their latests updates | U53: Retained
A54: Not Run | B54: GO-MAN-053 | C54: Applications | D54: Attempt to apply again to same project | E54: Duplicate application is blocked with clear message | F54: Duplicate apply blocked | G54: P0 | H54: Member Subscriber | I54: User already has pending/approved application | J54: Regression | R54: Core | S54: Not Run | U54: Retained
A55: Not Run | B55: GO-MAN-054 | C55: Applications | D55: Open own/team project; attempt to apply | E55: Application is blocked because user is already a project member | F55: Project member cannot apply | G55: P1 | H55: Project Team Member | I55: User is already owner/admin/team member of project | J55: Regression | R55: Core | S55: Not Run | U55: Retained
A56: Not Run | B56: GO-MAN-055 | C56: Applications | D56: Attempt application to project that is not hiring | E56: Application is blocked; user sees not accepting applications message | F56: Apply to non-hiring project blocked | G56: P0 | H56: Member Subscriber | I56: Project with completed/live/draft status exists | J56: Regression | R56: Core | S56: Not Run | U56: Retained
A57: Not Run | B57: GO-MAN-056 | C57: Applications | D57: Open project applications/admin area | E57: Owner sees applications for their project; applicant data and CV snapshot display correctly | F57: Owner views applications | G57: P0 | H57: Project Owner | I57: Project has applications | J57: Smoke | R57: Core | S57: Not Run | U57: Retained
A58: Not Run | B58: GO-MAN-057 | C58: Applications | D58: Attempt to open project applications endpoint/page for another owner's project | E58: Access is denied; application data is not visible | F58: Unrelated user cannot view applications | G58: P0 | H58: Unrelated User | I58: Project has applications | J58: Regression | R58: Core | S58: Not Run | U58: Retained
A59: Not Run | B59: GO-MAN-058 | C59: Applications | D59: Approve applicant | E59: Application status becomes approved; applicant is added to team members; applicant sees team/project membership | F59: Approve application | G59: P0 | H59: Project Owner | I59: Pending application exists | J59: Smoke | R59: Core | S59: Not Run | U59: Retained
A60: Not Run | B60: GO-MAN-059 | C60: Applications | D60: Reject applicant | E60: Application status becomes rejected; applicant is not added to project team | F60: Reject application | G60: P1 | H60: Project Owner | I60: Pending application exists | J60: Regression | R60: Core | S60: Not Run | U60: Retained
A61: Not Run | B61: GO-MAN-060 | C61: Applications | D61: Open own applications; cancel application | E61: Application status becomes cancelled; project team membership does not change | F61: Applicant cancels application | G61: P1 | H61: Member Subscriber | I61: Pending own application exists | J61: Regression | R61: Core | S61: Not Run | U61: Retained
A62: Not Run | B62: GO-MAN-061 | C62: Admin | D62: Open /admin and child admin URLs as visitor and non-admin user | E62: Access denied or redirected; no admin data visible | F62: Admin route protection | G62: P0 | H62: Visitor or Non-admin | I62: Admin pages exist | J62: Smoke | R62: Core | S62: Not Run | U62: Retained
A63: Not Run | B63: GO-MAN-062 | C63: Admin | D63: Open /admin/dashboard | E63: Dashboard loads without error; metrics/cards are visible and plausible | F63: Admin dashboard loads | G63: P0 | H63: Platform Admin | I63: Admin account active | J63: Regression | R63: Core | S63: Not Run | U63: Retained
A64: Not Run | B64: GO-MAN-063 | C64: Admin | D64: Open /admin/users; search/filter if available; inspect user details | E64: Users list loads; no sensitive secrets shown; admin actions are clear | F64: Admin users page | G64: P1 | H64: Platform Admin | I64: Users exist | J64: Regression | R64: Core | S64: Not Run | U64: Retained
A65: Not Run | B65: GO-MAN-064 | C65: Admin | D65: Open /admin/projects; filter statuses; open project actions | E65: Admin sees projects across owners; actions match permissions | F65: Admin projects page | G65: P0 | H65: Platform Admin | I65: Projects exist | J65: Regression | R65: Core | S65: Not Run | U65: Retained
... A74: Not Run | B74: GO-MAN-073 | C74: Billing | D74: Pay using card 4242 4242 4242 4242 future expiry any CVC | E74: Payment succeeds; user returns to success URL; no live payment is charged | F74: Sandbox payment success | G74: P0 | H74: Logged-in User | I74: Polar sandbox checkout opened Use controlled QA accounts and Polar sandbox only. | J74: Smoke | R74: Sandbox billing | S74: Not Run | U74: Retained
A75: Not Run | B75: GO-MAN-074 | C75: Billing | D75: Wait on success page after payment; refresh if needed | E75: Success page reflects activated subscription after webhook; user permissions update | F75: Success activation polling | G75: P0 | H75: Subscriber | I75: Payment completed and webhook configured Use controlled QA accounts and Polar sandbox only. | J75: Smoke | R75: Sandbox billing | S75: Not Run | T75: V 1.7 TEST: There are two You are an offical galactic omnivore member they might be a bug or a feature asking the user to do the same thing if they kill the pop-up. | U75: Retained
A76: Not Run | B76: GO-MAN-075 | C76: Billing | D76: After successful payment inspect users/{uid} orders subscription_events processed_webhooks | E76: User has activeMember membershipTier polarCustomerId subscriptionId subscriptionEndsAt; order/event/webhook docs exist | F76: Firestore subscription data | G76: P0 | H76: Subscriber | I76: Firebase console access available Use controlled QA accounts and Polar sandbox only. | J76: Extended | R76: Sandbox billing | S76: Retest | T76: V 1.7 TEST: All are pass except for processed_webhooks, because I don't know how to test them. | U76: Retained
A77: Not Run | B77: GO-MAN-076 | C77: Billing | D77: Open /billing | E77: Billing page shows active subscription status period end and portal/cancel controls | F77: Billing page active subscription | G77: P0 | H77: Subscriber | I77: Active subscription exists Use controlled QA accounts and Polar sandbox only. | J77: Smoke | R77: Sandbox billing | S77: Not Run | U77: Retained
A78: Not Run | B78: GO-MAN-077 | C78: Billing | D78: Click manage billing/portal button | E78: Polar portal opens using customer session; user sees own subscription only | F78: Billing portal opens | G78: P0 | H78: Subscriber | I78: polarCustomerId exists Use controlled QA accounts and Polar sandbox only. | J78: Smoke | R78: Sandbox billing | S78: Retest | T78: V 1.7 TEST: There is a regression, when you refresh the /billing page it redirects to sign in, but the user is already signed in, it's confusing, and takes a long time to get back to billing. And on top of that it allows me to exploit access to /subscription/success if I go back on the following URL "https://www.galacticomnivore.com/login?redirect=/billing" | U78: Retained
A79: Not Run | B79: GO-MAN-078 | C79: Billing | D79: Cancel via /billing or Polar portal; return to app; refresh billing | E79: Status becomes canceled; willRenew false; access remains until subscriptionEndsAt | F79: Cancel subscription | G79: P0 | H79: Subscriber | I79: Active sandbox subscription exists Use controlled QA accounts and Polar sandbox only. | J79: Smoke | R79: Sandbox billing | S79: Not Run | U79: Retained
A80: Not Run | B80: GO-MAN-079 | C80: Billing | D80: Redeliver same webhook event from Polar dashboard | E80: No duplicate order/event records are created; app state remains correct | F80: Webhook replay idempotency | G80: P0 | H80: Admin/Developer | I80: Polar dashboard webhook event available Use controlled QA accounts and Polar sandbox only. | J80: Extended | R80: Sandbox billing | S80: Blocked | T80: V 1.7 TEST: Need more details or will test with Dejan | U80: Retained
A81: Not Run | B81: GO-MAN-080 | C81: Billing | D81: Cause subscription.revoked or equivalent; refresh app as subscriber | E81: activeMember becomes false; member-only actions are blocked | F81: Revoked subscription access | G81: P0 | H81: Admin/Developer | I81: Sandbox revoked event can be triggered or simulated Use controlled QA accounts and Polar sandbox only. | J81: Extended | R81: Sandbox billing | S81: Blocked | T81: V 1.7 TEST: Need more details or will test with Dejan | U81: Retained
A82: Not Run | B82: GO-MAN-081 | C82: Billing | D82: Issue full refund in Polar sandbox; wait for webhook | E82: Order marked refunded; activeMember false; subscription/access state is correct | F82: Full refund access | G82: P0 | H82: Admin/Developer | I82: Sandbox paid order exists Use controlled QA accounts and Polar sandbox only. | J82: Extended | R82: Sandbox billing | S82: Blocked | T82: V 1.7 TEST: Need more details or will test with Dejan | U82: Retained
A83: Not Run | B83: GO-MAN-082 | C83: Billing | D83: Issue partial refund if supported; wait for webhook | E83: Order marked refunded/updated as appropriate; access is not unexpectedly revoked | F83: Partial refund access | G83: P1 | H83: Admin/Developer | I83: Sandbox paid order exists Use controlled QA accounts and Polar sandbox only. | J83: Extended | R83: Sandbox billing | S83: Blocked | T83: V 1.7 TEST: Need more details or will test with Dejan | U83: Retained
A84: Not Run | B84: GO-MAN-083 | C84: Billing | D84: Trigger subscription.updated with past_due behavior in staging/sandbox if possible | E84: User remains active during grace/retry window; lastPaymentFailed or status reflects past_due | F84: Past due grace | G84: P1 | H84: Admin/Developer | I84: Sandbox can trigger past_due or event replay Use controlled QA accounts and Polar sandbox only. | J84: Extended | R84: Sandbox billing | S84: Blocked | T84: V 1.7 TEST: Need more details or will test with Dejan | U84: Retained
A85: Not Run | B85: GO-MAN-084 | C85: Firestore Rules | D85: As unauthenticated or unrelated user attempt client read of private project | E85: Read is denied; only server/admin or project members can access as intended | F85: Private projects read protection | G85: P0 | H85: Developer | I85: Firebase Rules Playground or emulator available | J85: Extended | R85: Core | S85: Blocked | U85: Retained
A86: Not Run | B86: GO-MAN-085 | C86: Firestore Rules | D86: Attempt client read of draft/pending public project as visitor | E86: Read is denied or unavailable from client discovery path | F86: Draft/pending project protection | G86: P0 | H86: Developer | I86: Firebase Rules Playground or emulator available | J86: Extended | R86: Core | S86: Blocked | U86: Retained
A87: Not Run | B87: GO-MAN-086 | C87: Firestore Rules | D87: Attempt client read of orders collection as normal user | E87: Orders are not broadly readable; user cannot inspect other users' billing data | F87: Orders read protection | G87: P0 | H87: Developer | I87: Firebase Rules Playground or emulator available | J87: Extended | R87: Core | S87: Blocked | U87: Retained
A88: Not Run | B88: GO-MAN-087 | C88: Firestore Rules | D88: Attempt client read of subscription_events and processed_webhooks | E88: Reads are denied to normal users; sensitive webhook/payment metadata protected | F88: Subscription events protection | G88: P0 | H88: Developer | I88: Firebase Rules Playground or emulator available | J88: Extended | R88: Core | S88: Blocked | U88: Retained
A89: Not Run | B89: GO-MAN-088 | C89: Firestore Rules | D89: Attempt read/write applications as applicant owner unrelated user | E89: Applicant can access own allowed data; owner/admin can access project applications; unrelated user denied | F89: Applications protection | G89: P0 | H89: Developer | I89: Firebase Rules Playground or emulator available | J89: Extended | R89: Core | S89: Blocked | U89: Retained
A90: Not Run | B90: GO-MAN-089 | C90: Firestore Rules | D90: Attempt client reads of user_profiles/go_cvs for public private and project-creator visibility | E90: Visibility rules match profile/CV settings; private data denied | F90: CV/profile protection | G90: P0 | H90: Developer | I90: Firebase Rules Playground or emulator available | J90: Extended | R90: Core | S90: Blocked | U90: Retained
A91: Not Run | B91: GO-MAN-090 | C91: Firestore Rules | D91: Attempt normal-user client access to admin analytics/users/subscriptions source data | E91: Admin-only data is denied to non-admin clients | F91: Admin-only data protection | G91: P0 | H91: Developer | I91: Firebase Rules Playground or emulator available | J91: Extended | R91: Core | S91: Blocked | U91: Retained
A92: Not Run | B92: GO-MAN-091 | C92: UX | D92: Enter long form data; trigger validation error; inspect form values | E92: Valid entered data remains; only invalid fields need correction | F92: Form persistence after errors | G92: P1 | H92: Logged-in User | I92: Forms available | J92: Visual | R92: Core | S92: Not Run | U92: Retained
A93: Not Run | B93: GO-MAN-092 | C93: UX | D93: Throttle network; open project list billing CV and admin pages | E93: Loading states appear; no blank confusing screen; user can recover | F93: Loading states | G93: P1 | H93: Logged-in User | I93: Slow network throttling available | J93: Visual | R93: Core | S93: Not Run | U93: Retained
A94: Not Run | B94: GO-MAN-093 | C94: UX | D94: Disconnect network during save/apply/checkout route; observe UI | E94: User sees actionable error; app does not crash; retry is possible | F94: Error states | G94: P1 | H94: Logged-in User | I94: Can simulate failed request or disconnect network | J94: Visual | R94: Core | S94: Not Run | U94: Retained
A95: Not Run | B95: GO-MAN-094 | C95: UX | D95: Attempt delete/archive/cancel actions | E95: Destructive actions have confirmation and clear consequences | F95: Destructive confirmations | G95: P0 | H95: Project Owner/Admin | I95: Project exists | J95: Visual | R95: Core | S95: Not Run | U95: Retained
A96: Not Run | B96: GO-MAN-095 | C96: UX | D96: Use Tab Shift+Tab Enter Escape through nav forms dialogs drawers | E96: Focus is visible; controls are reachable; dialogs can be closed with expected keys | F96: Keyboard navigation | G96: P2 | H96: Logged-in User | I96: Desktop browser | J96: Visual | R96: Core | S96: Not Run | U96: Retained
... A675: Not Run | B675: GO-MAN-674 | C675: Baseline & Recovery | D675: During visual review log spacing, type, colors, copy and transition suggestions with a screenshot and linked test ID. | E675: Each suggestion is actionable in UX Backlog and remains separate from functional pass/fail unless it blocks use. | F675: Cosmetic observations backlog | G675: P2 | H675: Relevant QA personas | I675: Use prepared QA records and separate accounts. Record the actual URL and build on Run Overview. Use supported desktop and mobile browsers and a controlled failed-request fixture. | J675: Visual | R675: Core | S675: New | U675: New

Sheet UX Backlog
A2: UI, UX and motion backlog
A3: Capture observations during QA. Review prompts below are carried forward context, not newly verified defects.
A5: Item ID | B5: Area / Page | C5: Related Test / Source | D5: Type | E5: Observation | F5: Suggested change / decision | G5: Priority | H5: Status | I5: Evidence Link | J5: Owner | K5: Target round | L5: Acceptance check | M5: Reviewer decision | N5: Notes
A6: UX-001 | B6: Profile / Passport | C6: Known Issues #44 | D6: UX | E6: Prior note describes overlap between profile and Passport. | F6: Review purpose and navigation after the functional pass. | G6: P1 | H6: Review prompt | K6: After functional QA | L6: Distinct editing, learning and public-view destinations are understandable. | M6: Not reviewed | N6: Confirm current behavior before treating this as a defect.
A7: UX-002 | B7: Application rejection | C7: Known Issues #46 | D7: Product decision | E7: Prior request asks for rejection reasons and creator-controlled reapplication. | F7: Decide policy and message requirements before implementation. | G7: P1 | H7: Review prompt | K7: Future scope | L7: Approved behavior for reason, retry policy and status-change notice is documented. | M7: Not reviewed | N7: Current QA tests existing rejection only.
A8: UX-003 | B8: Avatar settings | C8: Known Issues #5 | D8: Product decision | E8: Generated/provider avatars exist. A prior request asks for custom upload/replacement. | F8: Decide supported avatar controls and storage requirements. | G8: P2 | H8: Review prompt | K8: Future scope | L8: Approved upload or generation behavior and limits are defined. | M8: Not reviewed
A9: UX-004 | B9: Motion baseline | C9: GO-MAN-673 | D9: Animation | E9: Capture existing motion before new animation work. | F9: Review baseline recordings and reduced-motion behavior. | G9: P2 | H9: Review prompt | K9: After functional QA | L9: Proposed motion has an equivalent reduced-motion state. | M9: Not reviewed | N9: This is a review task, not an observed animation defect.

Sheet V 1.8 TEST
A1: Status | B1: Test ID | C1: Suite | D1: Steps | E1: Expected Result | F1: Feature | G1: Priority | H1: Persona | I1: Preconditions | K1: Actual Result | L1: Notes | M1: Evidence Link | N1: Run Date
A2: Not Run | B2: GO-MAN-001 | C2: Public Website | D2: Open the home page; wait for the page to fully load; check above-the-fold content; scroll to bottom | E2: Home page loads without console-visible broken UI; main brand/content is clear; no missing critical images; footer is reachable | F2: Home page load | G2: P0 | H2: Visitor | I2: Production or local site is running
A3: Not Run | B3: GO-MAN-002 | C3: Public Website | D3: Open home page; click each main nav item; use browser back; repeat for logo/home link | E3: Every nav item routes to the expected page; no 404; active page content matches navigation label | F3: Desktop navigation | G3: P0 | H3: Visitor | I3: Site is running on desktop viewport
A4: Not Run | B4: GO-MAN-003 | C4: Public Website | D4: Resize to mobile or use phone; open mobile menu; tap every nav item; close and reopen menu | E4: Mobile menu is usable; links work; menu does not overlap content; menu can be dismissed | F4: Mobile navigation | G4: P0 | H4: Visitor | I4: Site is running on mobile viewport
A5: Not Run | B5: GO-MAN-004 | C5: Public Website | D5: Open home page; click primary CTA; return; click secondary CTAs; check destination pages | E5: CTAs route to intended signup/pricing/contact/project pages; labels match destination intent | F5: Landing CTAs | G5: P0 | H5: Visitor | I5: Site is running
A6: Not Run | B6: GO-MAN-005 | C6: Public Website | D6: Check home/pricing/projects/about/FAQ pages at 390px 768px and desktop widths | E6: No horizontal scrolling; text does not overlap; buttons fit; sections remain readable | F6: Responsive layout | G6: P1 | H6: Visitor | I6: Use desktop tablet and mobile widths
A7: Not Run | B7: GO-MAN-006 | C7: Public Website | D7: Open key public pages; look for broken images/icons; refresh once | E7: Images/icons render correctly; no obvious layout jumps due to missing assets | F7: Image and asset loading | G7: P1 | H7: Visitor | I7: Site is running
A8: Retest | B8: GO-MAN-007 | C8: Public Website | D8: Open FAQ; expand/collapse each FAQ item; check links if present | E8: FAQ controls work; content is readable; links open expected destinations | F8: FAQ page | G8: P1 | H8: Visitor | I8: FAQ page exists
A9: Retest | B9: GO-MAN-008 | C9: Public Website | D9: Open About; scan page content; test visible links/buttons | E9: About content is readable and current; links/buttons work; no typo-heavy or placeholder content | F9: About page | G9: P1 | H9: Visitor | I9: About page exists
A10: Not Run | B10: GO-MAN-009 | C10: Public Website | D10: Open pricing page; inspect all tiers and intervals; toggle monthly/annual if available | E10: Pricing is understandable; member vs company benefits are clear; checkout buttons are visible | F10: Pricing page | G10: P0 | H10: Visitor | I10: Polar products configured
A11: Not Run | B11: GO-MAN-010 | C11: Public Website | D11: Open a nonsense URL such as /this-page-does-not-exist | E11: User sees a graceful not-found or redirect experience; no raw error stack | F11: 404/not-found experience | G11: P2 | H11: Visitor | I11: Site is running
A12: Not Run | B12: GO-MAN-011 | C12: Auth | D12: Open signup; create account; complete required fields; submit | E12: Account is created; user lands on expected next page; no duplicate or confusing messages | F12: Signup flow | G12: P0 | H12: Visitor | I12: Test email available
A13: Not Run | B13: GO-MAN-012 | C13: Auth | D13: Open login; enter valid credentials; submit | E13: User logs in; protected nav/profile state appears; no unexpected redirect loop | F13: Login flow | G13: P0 | H13: Free User | I13: Existing account available
... A529: Not Run | B529: GO-MAN-528 | C529: Visual & Accessibility | D529: Using non-production data, open All new public, member, and administrator product surfaces. Prepare the state named “External-link indication”, perform the single relevant navigation or action, and record the visible result, resulting URL, HTTP status where applicable, and browser console/network errors. | E529: At “External-link indication”, content remains readable with no clipping or horizontal overflow; focus, labels, status meaning, touch targets, and motion behavior remain perceivable and operable. | F529: External-link indication | G529: P1 | H529: Visitor, keyboard user, screen-reader user, or administrator | I529: Use staging data for populated, empty, locked, loading, error, and confirmation states; reduced motion available. Use synthetic records and do not change production data.

Sheet  V 1.7 TEST
A1: Status | B1: Test ID | C1: Suite | D1: Steps | E1: Expected Result | F1: Feature | G1: Priority | H1: Persona | I1: Preconditions | K1: Actual Result | L1: Notes | M1: Evidence Link | N1: Run Date
A2: Not Run | B2: GO-MAN-001 | C2: Public Website | D2: Open the home page; wait for the page to fully load; check above-the-fold content; scroll to bottom | E2: Home page loads without console-visible broken UI; main brand/content is clear; no missing critical images; footer is reachable | F2: Home page load | G2: P0 | H2: Visitor | I2: Production or local site is running | K2: Functionally clean, however there are multiple improvements to be made on the Landing Page | L2: Bugs will be reported
A3: Not Run | B3: GO-MAN-002 | C3: Public Website | D3: Open home page; click each main nav item; use browser back; repeat for logo/home link | E3: Every nav item routes to the expected page; no 404; active page content matches navigation label | F3: Desktop navigation | G3: P0 | H3: Visitor | I3: Site is running on desktop viewport
A4: Not Run | B4: GO-MAN-003 | C4: Public Website | D4: Resize to mobile or use phone; open mobile menu; tap every nav item; close and reopen menu | E4: Mobile menu is usable; links work; menu does not overlap content; menu can be dismissed | F4: Mobile navigation | G4: P0 | H4: Visitor | I4: Site is running on mobile viewport
A5: Not Run | B5: GO-MAN-004 | C5: Public Website | D5: Open home page; click primary CTA; return; click secondary CTAs; check destination pages | E5: CTAs route to intended signup/pricing/contact/project pages; labels match destination intent | F5: Landing CTAs | G5: P0 | H5: Visitor | I5: Site is running
A6: Not Run | B6: GO-MAN-005 | C6: Public Website | D6: Check home/pricing/projects/about/FAQ pages at 390px 768px and desktop widths | E6: No horizontal scrolling; text does not overlap; buttons fit; sections remain readable | F6: Responsive layout | G6: P1 | H6: Visitor | I6: Use desktop tablet and mobile widths
A7: Not Run | B7: GO-MAN-006 | C7: Public Website | D7: Open key public pages; look for broken images/icons; refresh once | E7: Images/icons render correctly; no obvious layout jumps due to missing assets | F7: Image and asset loading | G7: P1 | H7: Visitor | I7: Site is running
A8: Retest | B8: GO-MAN-007 | C8: Public Website | D8: Open FAQ; expand/collapse each FAQ item; check links if present | E8: FAQ controls work; content is readable; links open expected destinations | F8: FAQ page | G8: P1 | H8: Visitor | I8: FAQ page exists | K8: Functionality is there but test is failed but the information is innacurate, we need to update the FAQ to reflect the real business proposition we are offering
A9: Retest | B9: GO-MAN-008 | C9: Public Website | D9: Open About; scan page content; test visible links/buttons | E9: About content is readable and current; links/buttons work; no typo-heavy or placeholder content | F9: About page | G9: P1 | H9: Visitor | I9: About page exists | K9: Functionality is there but test is failed but the information is innacurate, we need to update the ABOIT US to reflect the real business proposition we are offering
A10: Not Run | B10: GO-MAN-009 | C10: Public Website | D10: Open pricing page; inspect all tiers and intervals; toggle monthly/annual if available | E10: Pricing is understandable; member vs company benefits are clear; checkout buttons are visible | F10: Pricing page | G10: P0 | H10: Visitor | I10: Polar products configured | K10: We offer a community newsletter but we don't have one. See what we need in order to have one.
A11: Not Run | B11: GO-MAN-010 | C11: Public Website | D11: Open a nonsense URL such as /this-page-does-not-exist | E11: User sees a graceful not-found or redirect experience; no raw error stack | F11: 404/not-found experience | G11: P2 | H11: Visitor | I11: Site is running
A12: Not Run | B12: GO-MAN-011 | C12: Auth | D12: Open signup; create account; complete required fields; submit | E12: Account is created; user lands on expected next page; no duplicate or confusing messages | F12: Signup flow | G12: P0 | H12: Visitor | I12: Test email available
A13: Not Run | B13: GO-MAN-012 | C13: Auth | D13: Open login; enter valid credentials; submit | E13: User logs in; protected nav/profile state appears; no unexpected redirect loop | F13: Login flow | G13: P0 | H13: Free User | I13: Existing account available
A14: Not Run | B14: GO-MAN-013 | C14: Auth | D14: Enter invalid credentials; submit | E14: Clear error appears; password is not exposed; form remains usable | F14: Invalid login | G14: P1 | H14: Visitor | I14: Login page available
A15: Not Run | B15: GO-MAN-014 | C15: Auth | D15: Use profile/menu logout action; confirm logged-out state | E15: Session ends; protected links redirect or hide; public pages still work | F15: Logout flow | G15: P0 | H15: Logged-in User | I15: User is logged in
A16: Retest | B16: GO-MAN-015 | C16: Auth | D16: Open reset password; enter test account email; submit | E16: User receives success state; reset email is sent if email service is configured | F16: Password reset | G16: P1 | H16: Visitor | I16: Reset password page and email service configured | K16: Reset password throrws error Failed to send reset email. Please try again
A17: Not Run | B17: GO-MAN-016 | C17: Auth | D17: Open /dashboard /billing /admin /project/create directly | E17: Logged-out visitor is redirected or shown auth-required state; no protected data is visible | F17: Protected route redirect | G17: P0 | H17: Visitor | I17: Logged out
A18: Not Run | B18: GO-MAN-017 | C18: Auth | D18: Refresh current page; close and reopen browser tab; revisit site | E18: Session remains valid if expected; user identity and nav state are stable | F18: Session persistence | G18: P1 | H18: Logged-in User | I18: User is logged in
A19: Not Run | B19: GO-MAN-018 | C19: Onboarding | D19: Open onboarding page; begin onboarding flow | E19: Onboarding starts cleanly; first step is clear; progress is visible if expected | F19: Start onboarding | G19: P0 | H19: Logged-in User | I19: Logged in as member
A20: Not Run | B20: GO-MAN-019 | C20: Onboarding | D20: Complete every required onboarding step with valid values; submit final step | E20: Profile is saved; completion state appears; user can proceed to CV generation | F20: Complete required fields | G20: P0 | H20: Logged-in User | I20: Onboarding available
A21: Not Run | B21: GO-MAN-020 | C21: Onboarding | D21: Leave required fields empty; enter invalid URLs; exceed long text limits; submit | E21: Helpful validation errors appear; entered valid data is preserved; user can correct and continue | F21: Validation errors | G21: P1 | H21: Logged-in User | I21: Onboarding available
A22: Not Run | B22: GO-MAN-021 | C22: Onboarding | D22: Move forward several steps; go back; edit previous values; move forward again | E22: Previously entered values persist; progress remains correct; no data loss | F22: Back/forward navigation | G22: P1 | H22: Logged-in User | I22: Onboarding in progress
A23: Not Run | B23: GO-MAN-022 | C23: Onboarding | D23: Complete onboarding on mobile viewport | E23: Controls are tappable; inputs fit screen; progress and buttons remain visible | F23: Mobile onboarding | G23: P1 | H23: Logged-in User | I23: Mobile viewport
A24: Not Run | B24: GO-MAN-023 | C24: Profile | D24: Open profile page; inspect displayed fields | E24: Profile displays current user data; no private admin-only fields are shown | F24: View own profile | G24: P0 | H24: Logged-in User | I24: Profile data exists
A25: Not Run | B25: GO-MAN-024 | C25: Profile | D25: Edit display name role tools portfolio links and visibility settings; save | E25: Changes save successfully and persist after refresh | F25: Edit profile | G25: P0 | H25: Logged-in User | I25: Profile page available
A26: Not Run | B26: GO-MAN-025 | C26: Profile | D26: Enter social/portfolio URL without http/https; save | E26: Validation error appears; invalid URL is not silently accepted | F26: Profile invalid social URL | G26: P1 | H26: Logged-in User | I26: Profile editor available
A27: Not Run | B27: GO-MAN-026 | C27: Profile | D27: Toggle public/private or visibility settings; save; view from another account if possible | E27: Visibility settings persist and affect what other users can see | F27: Privacy settings | G27: P1 | H27: Logged-in User | I27: Profile editor available
A28: Not Run | B28: GO-MAN-027 | C28: CV | D28: Open CV page; click generate; wait for result | E28: CV is generated from profile data; title summary sections appear; no invented facts are obvious | F28: Generate CV | G28: P0 | H28: Logged-in User | I28: Onboarding profile completed
A29: Retest | B29: GO-MAN-028 | C29: CV | D29: Generate CV without AI service configured | E29: CV still generates with deterministic summary; user is not blocked by AI | F29: AI unavailable fallback | G29: P1 | H29: Logged-in User | I29: AI key disabled or unavailable in test env | K29: We will not be using AI for creation and updates of CV at the moment maybe in the future, all mentions for AI being used or consent formes need to be removed.
A30: Not Run | B30: GO-MAN-029 | C30: CV | D30: Edit CV title summary and at least one section; save | E30: Edits persist after refresh; formatting remains readable | F30: Edit CV | G30: P0 | H30: Logged-in User | I30: CV exists
A31: Not Run | B31: GO-MAN-030 | C31: CV | D31: Click publish/approve; confirm if prompted | E31: CV status becomes active/published; user receives clear success state | F31: Publish CV | G31: P0 | H31: Logged-in User | I31: Draft CV exists
A32: Not Run | B32: GO-MAN-031 | C32: CV | D32: Change CV visibility settings; view user/project application context from another account | E32: CV is visible only where expected based on settings | F32: CV visibility | G32: P1 | H32: Logged-in User | I32: CV exists and second account available
A33: Not Run | B33: GO-MAN-032 | C33: CV | D33: Open CV page; edit and publish on mobile | E33: CV editor and publish controls are usable; no clipped text/buttons | F33: CV mobile usability | G33: P1 | H33: Logged-in User | I33: Mobile viewport
A34: Not Run | B34: GO-MAN-033 | C34: Projects | D34: Open /projects while logged out; inspect visible projects | E34: Visitor sees only public discoverable projects; no private/draft/pending projects appear | F34: Project listing visitor | G34: P0 | H34: Visitor | I34: Projects exist with different statuses/visibility
A35: Not Run | B35: GO-MAN-034 | C35: Projects | D35: Open a public project detail page | E35: Project detail loads; visible fields are appropriate for visitor; apply controls require login/membership | F35: Project detail visitor | G35: P0 | H35: Visitor | I35: Public hiring/live/completed project exists
A36: Not Run | B36: GO-MAN-035 | C36: Projects | D36: Open private project URL as visitor/unrelated account | E36: Access is denied or redirected; private details are not visible | F36: Private project access | G36: P0 | H36: Visitor or unrelated user | I36: Private project exists
A37: Not Run | B37: GO-MAN-036 | C37: Projects | D37: Open /project/create; attempt project creation | E37: User is blocked with clear Company/Partner membership requirement | F37: Free user create block | G37: P0 | H37: Free User | I37: Logged in without active company membership
A38: Not Run | B38: GO-MAN-037 | C38: Projects | D38: Open /project/create; attempt project creation | E38: Member cannot create project; copy explains company tier requirement | F38: Member user create block | G38: P0 | H38: Member Subscriber | I38: Logged in with member tier only
A39: Retest | B39: GO-MAN-038 | C39: Projects | D39: Open /project/create; fill valid fields; choose new source project; submit | E39: Project is created as draft; source project is created; user becomes owner/admin/team member | F39: Company create project new source | G39: P0 | H39: Company Subscriber | I39: Company account active | K39: I should not be able to select source projects from other projects that I am not the owner of or I haven't created as a company subscriber. I also as a company subscriber should be able to see the projects I have created as drafts under my projects and allow me to edit them even though they are only in draft and not approved by the admin. I also managed to create duplicates projects somehow, the project i created is called TEST 5 maybe you can use some info in the way it was created to help you or I will try to catch .har file.
A40: Not Run | B40: GO-MAN-039 | C40: Projects | D40: Create another project using existing source project | E40: Project links to selected source project; source project project list updates | F40: Company create project existing source | G40: P1 | H40: Company Subscriber | I40: Company owns existing source project
A41: Not Run | B41: GO-MAN-040 | C41: Projects | D41: Submit empty form; enter invalid budget duration role visibility/type values | E41: Clear field errors appear; invalid project is not created | F41: Project form validation | G41: P0 | H41: Company Subscriber | I41: Project create form available
A42: Not Run | B42: GO-MAN-041 | C42: Projects | D42: Open project edit page; change title description budget duration roles; save | E42: Changes save and persist; owner remains authorized | F42: Owner edit draft | G42: P0 | H42: Project Owner | I42: Draft project exists
A43: Retest | B43: GO-MAN-042 | C43: Projects | D43: Attempt to change status to hiring/live/completed/rejected as non-admin owner | E43: Owner is blocked from admin-only status transitions | F43: Owner status restriction | G43: P0 | H43: Project Owner | I43: Draft project exists | K43: Users can update their project status. This must be stopped because it creates issues with admin, creator users can only observe the current status of their project and you can suggest to contact support if they want an update on their project.
A44: Not Run | B44: GO-MAN-043 | C44: Projects | D44: Open admin/project edit; set status to hiring; save | E44: Project becomes public/discoverable according to visibility and status | F44: Admin publish project | G44: P0 | H44: Platform Admin | I44: Draft/pending project exists
A45: Retest | B45: GO-MAN-044 | C45: Projects | D45: Set project status to rejected; save; check discovery | E45: Rejected project is hidden from public discovery; owner/admin can still inspect as intended | F45: Admin reject project | G45: P1 | H45: Platform Admin | I45: Project exists | K45: Owner cannot inspect it and it doesn't show in /myprojets it only can be seen in admin and can be updated to a different status.
A46: Not Run | B46: GO-MAN-045 | C46: Projects | D46: Archive project; refresh projects list; open direct URL as owner and unrelated user | E46: Archived project disappears from discovery; owner/admin can access; unrelated user cannot | F46: Archive project | G46: P1 | H46: Project Owner or Admin | I46: Project exists
A47: Not Run | B47: GO-MAN-046 | C47: Projects | D47: Restore/unarchive project if UI supports it; refresh list | E47: Project visibility returns according to status/visibility rules | F47: Restore project | G47: P1 | H47: Project Owner or Admin | I47: Archived project exists
A48: Not Run | B48: GO-MAN-047 | C48: Projects | D48: Delete project; confirm; check project list and direct URL | E48: Project is removed; direct URL no longer loads; related applications are removed or inaccessible | F48: Delete own project | G48: P0 | H48: Project Owner | I48: Owner project exists
A49: Retest | B49: GO-MAN-048 | C49: Projects | D49: Delete another user's project as admin; confirm | E49: Admin can delete; project disappears; owner no longer sees it | F49: Admin delete any project | G49: P0 | H49: Platform Admin | I49: Project owned by another user exists | K49: The admin user cannot delete a project, only archive it
A50: Not Run | B50: GO-MAN-049 | C50: Projects | D50: Attempt delete/edit project via UI/direct URL | E50: Access is denied; no project data changes | F50: Non-owner delete block | G50: P0 | H50: Unrelated User | I50: Project owned by another user exists
A51: Not Run | B51: GO-MAN-050 | C51: Applications | D51: Open hiring project; click apply; attempt application | E51: Free user is blocked with clear membership requirement | F51: Apply requires membership | G51: P0 | H51: Free User | I51: Public hiring project exists
A52: Not Run | B52: GO-MAN-051 | C52: Applications | D52: Open project; apply with role motivation availability | E52: Application is created as pending; user sees success; project owner can see it | F52: Member apply to hiring project | G52: P0 | H52: Member Subscriber | I52: Public hiring project exists and active CV exists
A53: Retest | B53: GO-MAN-052 | C53: Applications | D53: Apply to project; edit CV afterwards; inspect application as project owner/admin | E53: Application retains original CV snapshot; later CV edits do not alter historical application | F53: CV snapshot on apply | G53: P0 | H53: Member Subscriber | I53: CV exists and project accepts applications | K53: I want the creator to be able to see the moment the user applied and the current user profile as well two different links, the functionality is good as it is, but I also want creators to be able to observe public profiles with their latests updates
A54: Not Run | B54: GO-MAN-053 | C54: Applications | D54: Attempt to apply again to same project | E54: Duplicate application is blocked with clear message | F54: Duplicate apply blocked | G54: P0 | H54: Member Subscriber | I54: User already has pending/approved application
A55: Not Run | B55: GO-MAN-054 | C55: Applications | D55: Open own/team project; attempt to apply | E55: Application is blocked because user is already a project member | F55: Project member cannot apply | G55: P1 | H55: Project Team Member | I55: User is already owner/admin/team member of project
A56: Not Run | B56: GO-MAN-055 | C56: Applications | D56: Attempt application to project that is not hiring | E56: Application is blocked; user sees not accepting applications message | F56: Apply to non-hiring project blocked | G56: P0 | H56: Member Subscriber | I56: Project with completed/live/draft status exists
A57: Not Run | B57: GO-MAN-056 | C57: Applications | D57: Open project applications/admin area | E57: Owner sees applications for their project; applicant data and CV snapshot display correctly | F57: Owner views applications | G57: P0 | H57: Project Owner | I57: Project has applications
A58: Not Run | B58: GO-MAN-057 | C58: Applications | D58: Attempt to open project applications endpoint/page for another owner's project | E58: Access is denied; application data is not visible | F58: Unrelated user cannot view applications | G58: P0 | H58: Unrelated User | I58: Project has applications
A59: Not Run | B59: GO-MAN-058 | C59: Applications | D59: Approve applicant | E59: Application status becomes approved; applicant is added to team members; applicant sees team/project membership | F59: Approve application | G59: P0 | H59: Project Owner | I59: Pending application exists
A60: Not Run | B60: GO-MAN-059 | C60: Applications | D60: Reject applicant | E60: Application status becomes rejected; applicant is not added to project team | F60: Reject application | G60: P1 | H60: Project Owner | I60: Pending application exists
A61: Not Run | B61: GO-MAN-060 | C61: Applications | D61: Open own applications; cancel application | E61: Application status becomes cancelled; project team membership does not change | F61: Applicant cancels application | G61: P1 | H61: Member Subscriber | I61: Pending own application exists
A62: Not Run | B62: GO-MAN-061 | C62: Admin | D62: Open /admin and child admin URLs as visitor and non-admin user | E62: Access denied or redirected; no admin data visible | F62: Admin route protection | G62: P0 | H62: Visitor or Non-admin | I62: Admin pages exist
A63: Not Run | B63: GO-MAN-062 | C63: Admin | D63: Open /admin/dashboard | E63: Dashboard loads without error; metrics/cards are visible and plausible | F63: Admin dashboard loads | G63: P0 | H63: Platform Admin | I63: Admin account active
A64: Not Run | B64: GO-MAN-063 | C64: Admin | D64: Open /admin/users; search/filter if available; inspect user details | E64: Users list loads; no sensitive secrets shown; admin actions are clear | F64: Admin users page | G64: P1 | H64: Platform Admin | I64: Users exist
A65: Not Run | B65: GO-MAN-064 | C65: Admin | D65: Open /admin/projects; filter statuses; open project actions | E65: Admin sees projects across owners; actions match permissions | F65: Admin projects page | G65: P0 | H65: Platform Admin | I65: Projects exist
... A74: Not Run | B74: GO-MAN-073 | C74: Billing | D74: Pay using card 4242 4242 4242 4242 future expiry any CVC | E74: Payment succeeds; user returns to success URL; no live payment is charged | F74: Sandbox payment success | G74: P0 | H74: Logged-in User | I74: Polar sandbox checkout opened
A75: Not Run | B75: GO-MAN-074 | C75: Billing | D75: Wait on success page after payment; refresh if needed | E75: Success page reflects activated subscription after webhook; user permissions update | F75: Success activation polling | G75: P0 | H75: Subscriber | I75: Payment completed and webhook configured | L75: There are two You are an offical galactic omnivore member they might be a bug or a feature asking the user to do the same thing if they kill the pop-up.
A76: Retest | B76: GO-MAN-075 | C76: Billing | D76: After successful payment inspect users/{uid} orders subscription_events processed_webhooks | E76: User has activeMember membershipTier polarCustomerId subscriptionId subscriptionEndsAt; order/event/webhook docs exist | F76: Firestore subscription data | G76: P0 | H76: Subscriber | I76: Firebase console access available | K76: All are pass except for processed_webhooks, because I don't know how to test them.
A77: Not Run | B77: GO-MAN-076 | C77: Billing | D77: Open /billing | E77: Billing page shows active subscription status period end and portal/cancel controls | F77: Billing page active subscription | G77: P0 | H77: Subscriber | I77: Active subscription exists
A78: Retest | B78: GO-MAN-077 | C78: Billing | D78: Click manage billing/portal button | E78: Polar portal opens using customer session; user sees own subscription only | F78: Billing portal opens | G78: P0 | H78: Subscriber | I78: polarCustomerId exists | K78: There is a regression, when you refresh the /billing page it redirects to sign in, but the user is already signed in, it's confusing, and takes a long time to get back to billing. And on top of that it allows me to exploit access to /subscription/success if I go back on the following URL "https://www.galacticomnivore.com/login?redirect=/billing"
A79: Not Run | B79: GO-MAN-078 | C79: Billing | D79: Cancel via /billing or Polar portal; return to app; refresh billing | E79: Status becomes canceled; willRenew false; access remains until subscriptionEndsAt | F79: Cancel subscription | G79: P0 | H79: Subscriber | I79: Active sandbox subscription exists
A80: Blocked | B80: GO-MAN-079 | C80: Billing | D80: Redeliver same webhook event from Polar dashboard | E80: No duplicate order/event records are created; app state remains correct | F80: Webhook replay idempotency | G80: P0 | H80: Admin/Developer | I80: Polar dashboard webhook event available | K80: Need more details or will test with Dejan
A81: Blocked | B81: GO-MAN-080 | C81: Billing | D81: Cause subscription.revoked or equivalent; refresh app as subscriber | E81: activeMember becomes false; member-only actions are blocked | F81: Revoked subscription access | G81: P0 | H81: Admin/Developer | I81: Sandbox revoked event can be triggered or simulated | K81: Need more details or will test with Dejan
A82: Blocked | B82: GO-MAN-081 | C82: Billing | D82: Issue full refund in Polar sandbox; wait for webhook | E82: Order marked refunded; activeMember false; subscription/access state is correct | F82: Full refund access | G82: P0 | H82: Admin/Developer | I82: Sandbox paid order exists | K82: Need more details or will test with Dejan
A83: Blocked | B83: GO-MAN-082 | C83: Billing | D83: Issue partial refund if supported; wait for webhook | E83: Order marked refunded/updated as appropriate; access is not unexpectedly revoked | F83: Partial refund access | G83: P1 | H83: Admin/Developer | I83: Sandbox paid order exists | K83: Need more details or will test with Dejan
A84: Blocked | B84: GO-MAN-083 | C84: Billing | D84: Trigger subscription.updated with past_due behavior in staging/sandbox if possible | E84: User remains active during grace/retry window; lastPaymentFailed or status reflects past_due | F84: Past due grace | G84: P1 | H84: Admin/Developer | I84: Sandbox can trigger past_due or event replay | K84: Need more details or will test with Dejan
A85: Blocked | B85: GO-MAN-084 | C85: Firestore Rules | D85: As unauthenticated or unrelated user attempt client read of private project | E85: Read is denied; only server/admin or project members can access as intended | F85: Private projects read protection | G85: P0 | H85: Developer | I85: Firebase Rules Playground or emulator available
A86: Blocked | B86: GO-MAN-085 | C86: Firestore Rules | D86: Attempt client read of draft/pending public project as visitor | E86: Read is denied or unavailable from client discovery path | F86: Draft/pending project protection | G86: P0 | H86: Developer | I86: Firebase Rules Playground or emulator available
A87: Blocked | B87: GO-MAN-086 | C87: Firestore Rules | D87: Attempt client read of orders collection as normal user | E87: Orders are not broadly readable; user cannot inspect other users' billing data | F87: Orders read protection | G87: P0 | H87: Developer | I87: Firebase Rules Playground or emulator available
A88: Blocked | B88: GO-MAN-087 | C88: Firestore Rules | D88: Attempt client read of subscription_events and processed_webhooks | E88: Reads are denied to normal users; sensitive webhook/payment metadata protected | F88: Subscription events protection | G88: P0 | H88: Developer | I88: Firebase Rules Playground or emulator available
A89: Blocked | B89: GO-MAN-088 | C89: Firestore Rules | D89: Attempt read/write applications as applicant owner unrelated user | E89: Applicant can access own allowed data; owner/admin can access project applications; unrelated user denied | F89: Applications protection | G89: P0 | H89: Developer | I89: Firebase Rules Playground or emulator available
A90: Blocked | B90: GO-MAN-089 | C90: Firestore Rules | D90: Attempt client reads of user_profiles/go_cvs for public private and project-creator visibility | E90: Visibility rules match profile/CV settings; private data denied | F90: CV/profile protection | G90: P0 | H90: Developer | I90: Firebase Rules Playground or emulator available
A91: Blocked | B91: GO-MAN-090 | C91: Firestore Rules | D91: Attempt normal-user client access to admin analytics/users/subscriptions source data | E91: Admin-only data is denied to non-admin clients | F91: Admin-only data protection | G91: P0 | H91: Developer | I91: Firebase Rules Playground or emulator available
A92: Not Run | B92: GO-MAN-091 | C92: UX | D92: Enter long form data; trigger validation error; inspect form values | E92: Valid entered data remains; only invalid fields need correction | F92: Form persistence after errors | G92: P1 | H92: Logged-in User | I92: Forms available
A93: Not Run | B93: GO-MAN-092 | C93: UX | D93: Throttle network; open project list billing CV and admin pages | E93: Loading states appear; no blank confusing screen; user can recover | F93: Loading states | G93: P1 | H93: Logged-in User | I93: Slow network throttling available
A94: Not Run | B94: GO-MAN-093 | C94: UX | D94: Disconnect network during save/apply/checkout route; observe UI | E94: User sees actionable error; app does not crash; retry is possible | F94: Error states | G94: P1 | H94: Logged-in User | I94: Can simulate failed request or disconnect network
A95: Not Run | B95: GO-MAN-094 | C95: UX | D95: Attempt delete/archive/cancel actions | E95: Destructive actions have confirmation and clear consequences | F95: Destructive confirmations | G95: P0 | H95: Project Owner/Admin | I95: Project exists
A96: Not Run | B96: GO-MAN-095 | C96: UX | D96: Use Tab Shift+Tab Enter Escape through nav forms dialogs drawers | E96: Focus is visible; controls are reachable; dialogs can be closed with expected keys | F96: Keyboard navigation | G96: P2 | H96: Logged-in User | I96: Desktop browser
... A101: Blocked | B101: GO-MAN-100 | C101: Release | D101: Verify env vars webhook URL success URL Firestore rules bootstrap secret and Polar token mode | E101: Production uses production Polar token/product IDs; webhook points to production domain; bootstrap secret removed; rules deployed | F101: Production readiness | G101: P0 | H101: Developer | I101: Pre-launch environment configured

Sheet V 1.6 TEST
A1: Status | B1: Test ID | C1: Suite | D1: Steps | E1: Expected Result | F1: Feature | G1: Priority | H1: Persona | I1: Preconditions | K1: Actual Result | L1: Notes | M1: Evidence Link | N1: Run Date
A2: Pass | B2: GO-MAN-001 | C2: Public Website | D2: Open the home page; wait for the page to fully load; check above-the-fold content; scroll to bottom | E2: Home page loads without console-visible broken UI; main brand/content is clear; no missing critical images; footer is reachable | F2: Home page load | G2: P0 | H2: Visitor | I2: Production or local site is running | K2: Functionally clean, however there are multiple improvements to be made on the Landing Page | L2: Bugs will be reported
A3: Pass | B3: GO-MAN-002 | C3: Public Website | D3: Open home page; click each main nav item; use browser back; repeat for logo/home link | E3: Every nav item routes to the expected page; no 404; active page content matches navigation label | F3: Desktop navigation | G3: P0 | H3: Visitor | I3: Site is running on desktop viewport
A4: Pass | B4: GO-MAN-003 | C4: Public Website | D4: Resize to mobile or use phone; open mobile menu; tap every nav item; close and reopen menu | E4: Mobile menu is usable; links work; menu does not overlap content; menu can be dismissed | F4: Mobile navigation | G4: P0 | H4: Visitor | I4: Site is running on mobile viewport
A5: Pass | B5: GO-MAN-004 | C5: Public Website | D5: Open home page; click primary CTA; return; click secondary CTAs; check destination pages | E5: CTAs route to intended signup/pricing/contact/project pages; labels match destination intent | F5: Landing CTAs | G5: P0 | H5: Visitor | I5: Site is running
A6: Pass | B6: GO-MAN-005 | C6: Public Website | D6: Check home/pricing/projects/about/FAQ pages at 390px 768px and desktop widths | E6: No horizontal scrolling; text does not overlap; buttons fit; sections remain readable | F6: Responsive layout | G6: P1 | H6: Visitor | I6: Use desktop tablet and mobile widths
A7: Pass | B7: GO-MAN-006 | C7: Public Website | D7: Open key public pages; look for broken images/icons; refresh once | E7: Images/icons render correctly; no obvious layout jumps due to missing assets | F7: Image and asset loading | G7: P1 | H7: Visitor | I7: Site is running
A8: Fail | B8: GO-MAN-007 | C8: Public Website | D8: Open FAQ; expand/collapse each FAQ item; check links if present | E8: FAQ controls work; content is readable; links open expected destinations | F8: FAQ page | G8: P1 | H8: Visitor | I8: FAQ page exists | K8: Functionality is there but test is failed but the information is innacurate, we need to update the FAQ to reflect the real business proposition we are offering
A9: Fail | B9: GO-MAN-008 | C9: Public Website | D9: Open About; scan page content; test visible links/buttons | E9: About content is readable and current; links/buttons work; no typo-heavy or placeholder content | F9: About page | G9: P1 | H9: Visitor | I9: About page exists | K9: Functionality is there but test is failed but the information is innacurate, we need to update the ABOIT US to reflect the real business proposition we are offering
A10: Pass | B10: GO-MAN-009 | C10: Public Website | D10: Open pricing page; inspect all tiers and intervals; toggle monthly/annual if available | E10: Pricing is understandable; member vs company benefits are clear; checkout buttons are visible | F10: Pricing page | G10: P0 | H10: Visitor | I10: Polar products configured | K10: We offer a community newsletter but we don't have one. See what we need in order to have one.
A11: Pass | B11: GO-MAN-010 | C11: Public Website | D11: Open a nonsense URL such as /this-page-does-not-exist | E11: User sees a graceful not-found or redirect experience; no raw error stack | F11: 404/not-found experience | G11: P2 | H11: Visitor | I11: Site is running
A12: Pass | B12: GO-MAN-011 | C12: Auth | D12: Open signup; create account; complete required fields; submit | E12: Account is created; user lands on expected next page; no duplicate or confusing messages | F12: Signup flow | G12: P0 | H12: Visitor | I12: Test email available
A13: Pass | B13: GO-MAN-012 | C13: Auth | D13: Open login; enter valid credentials; submit | E13: User logs in; protected nav/profile state appears; no unexpected redirect loop | F13: Login flow | G13: P0 | H13: Free User | I13: Existing account available
A14: Pass | B14: GO-MAN-013 | C14: Auth | D14: Enter invalid credentials; submit | E14: Clear error appears; password is not exposed; form remains usable | F14: Invalid login | G14: P1 | H14: Visitor | I14: Login page available
A15: Pass | B15: GO-MAN-014 | C15: Auth | D15: Use profile/menu logout action; confirm logged-out state | E15: Session ends; protected links redirect or hide; public pages still work | F15: Logout flow | G15: P0 | H15: Logged-in User | I15: User is logged in
A16: Fail | B16: GO-MAN-015 | C16: Auth | D16: Open reset password; enter test account email; submit | E16: User receives success state; reset email is sent if email service is configured | F16: Password reset | G16: P1 | H16: Visitor | I16: Reset password page and email service configured | K16: Reset password throrws error Failed to send reset email. Please try again
A17: Pass | B17: GO-MAN-016 | C17: Auth | D17: Open /dashboard /billing /admin /project/create directly | E17: Logged-out visitor is redirected or shown auth-required state; no protected data is visible | F17: Protected route redirect | G17: P0 | H17: Visitor | I17: Logged out
A18: Pass | B18: GO-MAN-017 | C18: Auth | D18: Refresh current page; close and reopen browser tab; revisit site | E18: Session remains valid if expected; user identity and nav state are stable | F18: Session persistence | G18: P1 | H18: Logged-in User | I18: User is logged in
A19: Pass | B19: GO-MAN-018 | C19: Onboarding | D19: Open onboarding page; begin onboarding flow | E19: Onboarding starts cleanly; first step is clear; progress is visible if expected | F19: Start onboarding | G19: P0 | H19: Logged-in User | I19: Logged in as member
A20: Pass | B20: GO-MAN-019 | C20: Onboarding | D20: Complete every required onboarding step with valid values; submit final step | E20: Profile is saved; completion state appears; user can proceed to CV generation | F20: Complete required fields | G20: P0 | H20: Logged-in User | I20: Onboarding available
A21: Pass | B21: GO-MAN-020 | C21: Onboarding | D21: Leave required fields empty; enter invalid URLs; exceed long text limits; submit | E21: Helpful validation errors appear; entered valid data is preserved; user can correct and continue | F21: Validation errors | G21: P1 | H21: Logged-in User | I21: Onboarding available
A22: Pass | B22: GO-MAN-021 | C22: Onboarding | D22: Move forward several steps; go back; edit previous values; move forward again | E22: Previously entered values persist; progress remains correct; no data loss | F22: Back/forward navigation | G22: P1 | H22: Logged-in User | I22: Onboarding in progress
A23: Pass | B23: GO-MAN-022 | C23: Onboarding | D23: Complete onboarding on mobile viewport | E23: Controls are tappable; inputs fit screen; progress and buttons remain visible | F23: Mobile onboarding | G23: P1 | H23: Logged-in User | I23: Mobile viewport
A24: Pass | B24: GO-MAN-023 | C24: Profile | D24: Open profile page; inspect displayed fields | E24: Profile displays current user data; no private admin-only fields are shown | F24: View own profile | G24: P0 | H24: Logged-in User | I24: Profile data exists
A25: Pass | B25: GO-MAN-024 | C25: Profile | D25: Edit display name role tools portfolio links and visibility settings; save | E25: Changes save successfully and persist after refresh | F25: Edit profile | G25: P0 | H25: Logged-in User | I25: Profile page available
A26: Pass | B26: GO-MAN-025 | C26: Profile | D26: Enter social/portfolio URL without http/https; save | E26: Validation error appears; invalid URL is not silently accepted | F26: Profile invalid social URL | G26: P1 | H26: Logged-in User | I26: Profile editor available
A27: Pass | B27: GO-MAN-026 | C27: Profile | D27: Toggle public/private or visibility settings; save; view from another account if possible | E27: Visibility settings persist and affect what other users can see | F27: Privacy settings | G27: P1 | H27: Logged-in User | I27: Profile editor available
A28: Pass | B28: GO-MAN-027 | C28: CV | D28: Open CV page; click generate; wait for result | E28: CV is generated from profile data; title summary sections appear; no invented facts are obvious | F28: Generate CV | G28: P0 | H28: Logged-in User | I28: Onboarding profile completed
A29: Fail | B29: GO-MAN-028 | C29: CV | D29: Generate CV without AI service configured | E29: CV still generates with deterministic summary; user is not blocked by AI | F29: AI unavailable fallback | G29: P1 | H29: Logged-in User | I29: AI key disabled or unavailable in test env | K29: We will not be using AI for creation and updates of CV at the moment maybe in the future, all mentions for AI being used or consent formes need to be removed.
A30: Pass | B30: GO-MAN-029 | C30: CV | D30: Edit CV title summary and at least one section; save | E30: Edits persist after refresh; formatting remains readable | F30: Edit CV | G30: P0 | H30: Logged-in User | I30: CV exists
A31: Pass | B31: GO-MAN-030 | C31: CV | D31: Click publish/approve; confirm if prompted | E31: CV status becomes active/published; user receives clear success state | F31: Publish CV | G31: P0 | H31: Logged-in User | I31: Draft CV exists
A32: Pass | B32: GO-MAN-031 | C32: CV | D32: Change CV visibility settings; view user/project application context from another account | E32: CV is visible only where expected based on settings | F32: CV visibility | G32: P1 | H32: Logged-in User | I32: CV exists and second account available
A33: Pass | B33: GO-MAN-032 | C33: CV | D33: Open CV page; edit and publish on mobile | E33: CV editor and publish controls are usable; no clipped text/buttons | F33: CV mobile usability | G33: P1 | H33: Logged-in User | I33: Mobile viewport
A34: Pass | B34: GO-MAN-033 | C34: Projects | D34: Open /projects while logged out; inspect visible projects | E34: Visitor sees only public discoverable projects; no private/draft/pending projects appear | F34: Project listing visitor | G34: P0 | H34: Visitor | I34: Projects exist with different statuses/visibility
A35: Pass | B35: GO-MAN-034 | C35: Projects | D35: Open a public project detail page | E35: Project detail loads; visible fields are appropriate for visitor; apply controls require login/membership | F35: Project detail visitor | G35: P0 | H35: Visitor | I35: Public hiring/live/completed project exists
A36: Pass | B36: GO-MAN-035 | C36: Projects | D36: Open private project URL as visitor/unrelated account | E36: Access is denied or redirected; private details are not visible | F36: Private project access | G36: P0 | H36: Visitor or unrelated user | I36: Private project exists
A37: Pass | B37: GO-MAN-036 | C37: Projects | D37: Open /project/create; attempt project creation | E37: User is blocked with clear Company/Partner membership requirement | F37: Free user create block | G37: P0 | H37: Free User | I37: Logged in without active company membership
A38: Pass | B38: GO-MAN-037 | C38: Projects | D38: Open /project/create; attempt project creation | E38: Member cannot create project; copy explains company tier requirement | F38: Member user create block | G38: P0 | H38: Member Subscriber | I38: Logged in with member tier only
A39: Fail | B39: GO-MAN-038 | C39: Projects | D39: Open /project/create; fill valid fields; choose new source project; submit | E39: Project is created as draft; source project is created; user becomes owner/admin/team member | F39: Company create project new source | G39: P0 | H39: Company Subscriber | I39: Company account active | K39: I should not be able to select source projects from other projects that I am not the owner of or I haven't created as a company subscriber. I also as a company subscriber should be able to see the projects I have created as drafts under my projects and allow me to edit them even though they are only in draft and not approved by the admin. I also managed to create duplicates projects somehow, the project i created is called TEST 5 maybe you can use some info in the way it was created to help you or I will try to catch .har file.
A40: Pass | B40: GO-MAN-039 | C40: Projects | D40: Create another project using existing source project | E40: Project links to selected source project; source project project list updates | F40: Company create project existing source | G40: P1 | H40: Company Subscriber | I40: Company owns existing source project
A41: Pass | B41: GO-MAN-040 | C41: Projects | D41: Submit empty form; enter invalid budget duration role visibility/type values | E41: Clear field errors appear; invalid project is not created | F41: Project form validation | G41: P0 | H41: Company Subscriber | I41: Project create form available
A42: Pass | B42: GO-MAN-041 | C42: Projects | D42: Open project edit page; change title description budget duration roles; save | E42: Changes save and persist; owner remains authorized | F42: Owner edit draft | G42: P0 | H42: Project Owner | I42: Draft project exists
A43: Fail | B43: GO-MAN-042 | C43: Projects | D43: Attempt to change status to hiring/live/completed/rejected as non-admin owner | E43: Owner is blocked from admin-only status transitions | F43: Owner status restriction | G43: P0 | H43: Project Owner | I43: Draft project exists | K43: Users can update their project status. This must be stopped because it creates issues with admin, creator users can only observe the current status of their project and you can suggest to contact support if they want an update on their project.
A44: Pass | B44: GO-MAN-043 | C44: Projects | D44: Open admin/project edit; set status to hiring; save | E44: Project becomes public/discoverable according to visibility and status | F44: Admin publish project | G44: P0 | H44: Platform Admin | I44: Draft/pending project exists
A45: Fail | B45: GO-MAN-044 | C45: Projects | D45: Set project status to rejected; save; check discovery | E45: Rejected project is hidden from public discovery; owner/admin can still inspect as intended | F45: Admin reject project | G45: P1 | H45: Platform Admin | I45: Project exists | K45: Owner cannot inspect it and it doesn't show in /myprojets it only can be seen in admin and can be updated to a different status.
A46: Pass | B46: GO-MAN-045 | C46: Projects | D46: Archive project; refresh projects list; open direct URL as owner and unrelated user | E46: Archived project disappears from discovery; owner/admin can access; unrelated user cannot | F46: Archive project | G46: P1 | H46: Project Owner or Admin | I46: Project exists
A47: Pass | B47: GO-MAN-046 | C47: Projects | D47: Restore/unarchive project if UI supports it; refresh list | E47: Project visibility returns according to status/visibility rules | F47: Restore project | G47: P1 | H47: Project Owner or Admin | I47: Archived project exists
A48: Pass | B48: GO-MAN-047 | C48: Projects | D48: Delete project; confirm; check project list and direct URL | E48: Project is removed; direct URL no longer loads; related applications are removed or inaccessible | F48: Delete own project | G48: P0 | H48: Project Owner | I48: Owner project exists
A49: Fail | B49: GO-MAN-048 | C49: Projects | D49: Delete another user's project as admin; confirm | E49: Admin can delete; project disappears; owner no longer sees it | F49: Admin delete any project | G49: P0 | H49: Platform Admin | I49: Project owned by another user exists | K49: The admin user cannot delete a project, only archive it
A50: Pass | B50: GO-MAN-049 | C50: Projects | D50: Attempt delete/edit project via UI/direct URL | E50: Access is denied; no project data changes | F50: Non-owner delete block | G50: P0 | H50: Unrelated User | I50: Project owned by another user exists
A51: Pass | B51: GO-MAN-050 | C51: Applications | D51: Open hiring project; click apply; attempt application | E51: Free user is blocked with clear membership requirement | F51: Apply requires membership | G51: P0 | H51: Free User | I51: Public hiring project exists
A52: Pass | B52: GO-MAN-051 | C52: Applications | D52: Open project; apply with role motivation availability | E52: Application is created as pending; user sees success; project owner can see it | F52: Member apply to hiring project | G52: P0 | H52: Member Subscriber | I52: Public hiring project exists and active CV exists
A53: Fail | B53: GO-MAN-052 | C53: Applications | D53: Apply to project; edit CV afterwards; inspect application as project owner/admin | E53: Application retains original CV snapshot; later CV edits do not alter historical application | F53: CV snapshot on apply | G53: P0 | H53: Member Subscriber | I53: CV exists and project accepts applications | K53: I want the creator to be able to see the moment the user applied and the current user profile as well two different links, the functionality is good as it is, but I also want creators to be able to observe public profiles with their latests updates
A54: Pass | B54: GO-MAN-053 | C54: Applications | D54: Attempt to apply again to same project | E54: Duplicate application is blocked with clear message | F54: Duplicate apply blocked | G54: P0 | H54: Member Subscriber | I54: User already has pending/approved application
A55: Pass | B55: GO-MAN-054 | C55: Applications | D55: Open own/team project; attempt to apply | E55: Application is blocked because user is already a project member | F55: Project member cannot apply | G55: P1 | H55: Project Team Member | I55: User is already owner/admin/team member of project
A56: Pass | B56: GO-MAN-055 | C56: Applications | D56: Attempt application to project that is not hiring | E56: Application is blocked; user sees not accepting applications message | F56: Apply to non-hiring project blocked | G56: P0 | H56: Member Subscriber | I56: Project with completed/live/draft status exists
A57: Pass | B57: GO-MAN-056 | C57: Applications | D57: Open project applications/admin area | E57: Owner sees applications for their project; applicant data and CV snapshot display correctly | F57: Owner views applications | G57: P0 | H57: Project Owner | I57: Project has applications
A58: Pass | B58: GO-MAN-057 | C58: Applications | D58: Attempt to open project applications endpoint/page for another owner's project | E58: Access is denied; application data is not visible | F58: Unrelated user cannot view applications | G58: P0 | H58: Unrelated User | I58: Project has applications
A59: Pass | B59: GO-MAN-058 | C59: Applications | D59: Approve applicant | E59: Application status becomes approved; applicant is added to team members; applicant sees team/project membership | F59: Approve application | G59: P0 | H59: Project Owner | I59: Pending application exists
A60: Pass | B60: GO-MAN-059 | C60: Applications | D60: Reject applicant | E60: Application status becomes rejected; applicant is not added to project team | F60: Reject application | G60: P1 | H60: Project Owner | I60: Pending application exists
A61: Pass | B61: GO-MAN-060 | C61: Applications | D61: Open own applications; cancel application | E61: Application status becomes cancelled; project team membership does not change | F61: Applicant cancels application | G61: P1 | H61: Member Subscriber | I61: Pending own application exists
A62: Pass | B62: GO-MAN-061 | C62: Admin | D62: Open /admin and child admin URLs as visitor and non-admin user | E62: Access denied or redirected; no admin data visible | F62: Admin route protection | G62: P0 | H62: Visitor or Non-admin | I62: Admin pages exist
A63: Pass | B63: GO-MAN-062 | C63: Admin | D63: Open /admin/dashboard | E63: Dashboard loads without error; metrics/cards are visible and plausible | F63: Admin dashboard loads | G63: P0 | H63: Platform Admin | I63: Admin account active
A64: Pass | B64: GO-MAN-063 | C64: Admin | D64: Open /admin/users; search/filter if available; inspect user details | E64: Users list loads; no sensitive secrets shown; admin actions are clear | F64: Admin users page | G64: P1 | H64: Platform Admin | I64: Users exist
A65: Pass | B65: GO-MAN-064 | C65: Admin | D65: Open /admin/projects; filter statuses; open project actions | E65: Admin sees projects across owners; actions match permissions | F65: Admin projects page | G65: P0 | H65: Platform Admin | I65: Projects exist
... A74: Pass | B74: GO-MAN-073 | C74: Billing | D74: Pay using card 4242 4242 4242 4242 future expiry any CVC | E74: Payment succeeds; user returns to success URL; no live payment is charged | F74: Sandbox payment success | G74: P0 | H74: Logged-in User | I74: Polar sandbox checkout opened
A75: Pass | B75: GO-MAN-074 | C75: Billing | D75: Wait on success page after payment; refresh if needed | E75: Success page reflects activated subscription after webhook; user permissions update | F75: Success activation polling | G75: P0 | H75: Subscriber | I75: Payment completed and webhook configured | L75: There are two You are an offical galactic omnivore member they might be a bug or a feature asking the user to do the same thing if they kill the pop-up.
A76: Retest | B76: GO-MAN-075 | C76: Billing | D76: After successful payment inspect users/{uid} orders subscription_events processed_webhooks | E76: User has activeMember membershipTier polarCustomerId subscriptionId subscriptionEndsAt; order/event/webhook docs exist | F76: Firestore subscription data | G76: P0 | H76: Subscriber | I76: Firebase console access available | K76: All are pass except for processed_webhooks, because I don't know how to test them.
A77: Pass | B77: GO-MAN-076 | C77: Billing | D77: Open /billing | E77: Billing page shows active subscription status period end and portal/cancel controls | F77: Billing page active subscription | G77: P0 | H77: Subscriber | I77: Active subscription exists
A78: Retest | B78: GO-MAN-077 | C78: Billing | D78: Click manage billing/portal button | E78: Polar portal opens using customer session; user sees own subscription only | F78: Billing portal opens | G78: P0 | H78: Subscriber | I78: polarCustomerId exists | K78: There is a regression, when you refresh the /billing page it redirects to sign in, but the user is already signed in, it's confusing, and takes a long time to get back to billing. And on top of that it allows me to exploit access to /subscription/success if I go back on the following URL "https://www.galacticomnivore.com/login?redirect=/billing"
A79: Pass | B79: GO-MAN-078 | C79: Billing | D79: Cancel via /billing or Polar portal; return to app; refresh billing | E79: Status becomes canceled; willRenew false; access remains until subscriptionEndsAt | F79: Cancel subscription | G79: P0 | H79: Subscriber | I79: Active sandbox subscription exists
A80: Blocked | B80: GO-MAN-079 | C80: Billing | D80: Redeliver same webhook event from Polar dashboard | E80: No duplicate order/event records are created; app state remains correct | F80: Webhook replay idempotency | G80: P0 | H80: Admin/Developer | I80: Polar dashboard webhook event available | K80: Need more details or will test with Dejan
A81: Blocked | B81: GO-MAN-080 | C81: Billing | D81: Cause subscription.revoked or equivalent; refresh app as subscriber | E81: activeMember becomes false; member-only actions are blocked | F81: Revoked subscription access | G81: P0 | H81: Admin/Developer | I81: Sandbox revoked event can be triggered or simulated | K81: Need more details or will test with Dejan
A82: Blocked | B82: GO-MAN-081 | C82: Billing | D82: Issue full refund in Polar sandbox; wait for webhook | E82: Order marked refunded; activeMember false; subscription/access state is correct | F82: Full refund access | G82: P0 | H82: Admin/Developer | I82: Sandbox paid order exists | K82: Need more details or will test with Dejan
A83: Blocked | B83: GO-MAN-082 | C83: Billing | D83: Issue partial refund if supported; wait for webhook | E83: Order marked refunded/updated as appropriate; access is not unexpectedly revoked | F83: Partial refund access | G83: P1 | H83: Admin/Developer | I83: Sandbox paid order exists | K83: Need more details or will test with Dejan
A84: Blocked | B84: GO-MAN-083 | C84: Billing | D84: Trigger subscription.updated with past_due behavior in staging/sandbox if possible | E84: User remains active during grace/retry window; lastPaymentFailed or status reflects past_due | F84: Past due grace | G84: P1 | H84: Admin/Developer | I84: Sandbox can trigger past_due or event replay | K84: Need more details or will test with Dejan
A85: Blocked | B85: GO-MAN-084 | C85: Firestore Rules | D85: As unauthenticated or unrelated user attempt client read of private project | E85: Read is denied; only server/admin or project members can access as intended | F85: Private projects read protection | G85: P0 | H85: Developer | I85: Firebase Rules Playground or emulator available
A86: Blocked | B86: GO-MAN-085 | C86: Firestore Rules | D86: Attempt client read of draft/pending public project as visitor | E86: Read is denied or unavailable from client discovery path | F86: Draft/pending project protection | G86: P0 | H86: Developer | I86: Firebase Rules Playground or emulator available
A87: Blocked | B87: GO-MAN-086 | C87: Firestore Rules | D87: Attempt client read of orders collection as normal user | E87: Orders are not broadly readable; user cannot inspect other users' billing data | F87: Orders read protection | G87: P0 | H87: Developer | I87: Firebase Rules Playground or emulator available
A88: Blocked | B88: GO-MAN-087 | C88: Firestore Rules | D88: Attempt client read of subscription_events and processed_webhooks | E88: Reads are denied to normal users; sensitive webhook/payment metadata protected | F88: Subscription events protection | G88: P0 | H88: Developer | I88: Firebase Rules Playground or emulator available
A89: Blocked | B89: GO-MAN-088 | C89: Firestore Rules | D89: Attempt read/write applications as applicant owner unrelated user | E89: Applicant can access own allowed data; owner/admin can access project applications; unrelated user denied | F89: Applications protection | G89: P0 | H89: Developer | I89: Firebase Rules Playground or emulator available
A90: Blocked | B90: GO-MAN-089 | C90: Firestore Rules | D90: Attempt client reads of user_profiles/go_cvs for public private and project-creator visibility | E90: Visibility rules match profile/CV settings; private data denied | F90: CV/profile protection | G90: P0 | H90: Developer | I90: Firebase Rules Playground or emulator available
A91: Blocked | B91: GO-MAN-090 | C91: Firestore Rules | D91: Attempt normal-user client access to admin analytics/users/subscriptions source data | E91: Admin-only data is denied to non-admin clients | F91: Admin-only data protection | G91: P0 | H91: Developer | I91: Firebase Rules Playground or emulator available
A92: Pass | B92: GO-MAN-091 | C92: UX | D92: Enter long form data; trigger validation error; inspect form values | E92: Valid entered data remains; only invalid fields need correction | F92: Form persistence after errors | G92: P1 | H92: Logged-in User | I92: Forms available
A93: Not Run | B93: GO-MAN-092 | C93: UX | D93: Throttle network; open project list billing CV and admin pages | E93: Loading states appear; no blank confusing screen; user can recover | F93: Loading states | G93: P1 | H93: Logged-in User | I93: Slow network throttling available
A94: Not Run | B94: GO-MAN-093 | C94: UX | D94: Disconnect network during save/apply/checkout route; observe UI | E94: User sees actionable error; app does not crash; retry is possible | F94: Error states | G94: P1 | H94: Logged-in User | I94: Can simulate failed request or disconnect network
A95: Pass | B95: GO-MAN-094 | C95: UX | D95: Attempt delete/archive/cancel actions | E95: Destructive actions have confirmation and clear consequences | F95: Destructive confirmations | G95: P0 | H95: Project Owner/Admin | I95: Project exists
A96: Not Run | B96: GO-MAN-095 | C96: UX | D96: Use Tab Shift+Tab Enter Escape through nav forms dialogs drawers | E96: Focus is visible; controls are reachable; dialogs can be closed with expected keys | F96: Keyboard navigation | G96: P2 | H96: Logged-in User | I96: Desktop browser
... A101: Blocked | B101: GO-MAN-100 | C101: Release | D101: Verify env vars webhook URL success URL Firestore rules bootstrap secret and Polar token mode | E101: Production uses production Polar token/product IDs; webhook points to production domain; bootstrap secret removed; rules deployed | F101: Production readiness | G101: P0 | H101: Developer | I101: Pre-launch environment configured

Sheet V 1.5 TEST
A1: Status | B1: Test ID | C1: Suite | D1: Feature | E1: Priority | F1: Persona | G1: Preconditions | H1: Steps | I1: Expected Result | J1: Actual Result | K1: Notes | L1: Evidence Link | M1: Run Date
A2: Retest | B2: GO-MAN-001 | C2: Public Website | D2: Home page load | E2: P0 | F2: Visitor | G2: Production or local site is running | H2: Open the home page; wait for the page to fully load; check above-the-fold content; scroll to bottom | I2: Home page loads without console-visible broken UI; main brand/content is clear; no missing critical images; footer is reachable | J2: Functionally clean, however there are multiple improvements to be made on the Landing Page | K2: Bugs will be reported
A3: Pass | B3: GO-MAN-002 | C3: Public Website | D3: Desktop navigation | E3: P0 | F3: Visitor | G3: Site is running on desktop viewport | H3: Open home page; click each main nav item; use browser back; repeat for logo/home link | I3: Every nav item routes to the expected page; no 404; active page content matches navigation label
A4: Pass | B4: GO-MAN-003 | C4: Public Website | D4: Mobile navigation | E4: P0 | F4: Visitor | G4: Site is running on mobile viewport | H4: Resize to mobile or use phone; open mobile menu; tap every nav item; close and reopen menu | I4: Mobile menu is usable; links work; menu does not overlap content; menu can be dismissed
A5: Pass | B5: GO-MAN-004 | C5: Public Website | D5: Landing CTAs | E5: P0 | F5: Visitor | G5: Site is running | H5: Open home page; click primary CTA; return; click secondary CTAs; check destination pages | I5: CTAs route to intended signup/pricing/contact/project pages; labels match destination intent
A6: Pass | B6: GO-MAN-005 | C6: Public Website | D6: Responsive layout | E6: P1 | F6: Visitor | G6: Use desktop tablet and mobile widths | H6: Check home/pricing/projects/about/FAQ pages at 390px 768px and desktop widths | I6: No horizontal scrolling; text does not overlap; buttons fit; sections remain readable
A7: Pass | B7: GO-MAN-006 | C7: Public Website | D7: Image and asset loading | E7: P1 | F7: Visitor | G7: Site is running | H7: Open key public pages; look for broken images/icons; refresh once | I7: Images/icons render correctly; no obvious layout jumps due to missing assets
A8: Retest | B8: GO-MAN-007 | C8: Public Website | D8: FAQ page | E8: P1 | F8: Visitor | G8: FAQ page exists | H8: Open FAQ; expand/collapse each FAQ item; check links if present | I8: FAQ controls work; content is readable; links open expected destinations | J8: Test is passed but the information is innacurate, we need to update the FAQ to reflect the real business proposition we are offering
A9: Retest | B9: GO-MAN-008 | C9: Public Website | D9: About page | E9: P1 | F9: Visitor | G9: About page exists | H9: Open About; scan page content; test visible links/buttons | I9: About content is readable and current; links/buttons work; no typo-heavy or placeholder content | J9: Same as FAQ
A10: Retest | B10: GO-MAN-009 | C10: Public Website | D10: Pricing page | E10: P0 | F10: Visitor | G10: Polar products configured | H10: Open pricing page; inspect all tiers and intervals; toggle monthly/annual if available | I10: Pricing is understandable; member vs company benefits are clear; checkout buttons are visible | J10: We offer a community newsletter but we don't have one. See what we need in order to have one.
A11: Pass | B11: GO-MAN-010 | C11: Public Website | D11: 404/not-found experience | E11: P2 | F11: Visitor | G11: Site is running | H11: Open a nonsense URL such as /this-page-does-not-exist | I11: User sees a graceful not-found or redirect experience; no raw error stack
A12: Pass | B12: GO-MAN-011 | C12: Auth | D12: Signup flow | E12: P0 | F12: Visitor | G12: Test email available | H12: Open signup; create account; complete required fields; submit | I12: Account is created; user lands on expected next page; no duplicate or confusing messages
A13: Pass | B13: GO-MAN-012 | C13: Auth | D13: Login flow | E13: P0 | F13: Free User | G13: Existing account available | H13: Open login; enter valid credentials; submit | I13: User logs in; protected nav/profile state appears; no unexpected redirect loop
A14: Pass | B14: GO-MAN-013 | C14: Auth | D14: Invalid login | E14: P1 | F14: Visitor | G14: Login page available | H14: Enter invalid credentials; submit | I14: Clear error appears; password is not exposed; form remains usable
A15: Pass | B15: GO-MAN-014 | C15: Auth | D15: Logout flow | E15: P0 | F15: Logged-in User | G15: User is logged in | H15: Use profile/menu logout action; confirm logged-out state | I15: Session ends; protected links redirect or hide; public pages still work
A16: Pass | B16: GO-MAN-015 | C16: Auth | D16: Password reset | E16: P1 | F16: Visitor | G16: Reset password page and email service configured | H16: Open reset password; enter test account email; submit | I16: User receives success state; reset email is sent if email service is configured
A17: Pass | B17: GO-MAN-016 | C17: Auth | D17: Protected route redirect | E17: P0 | F17: Visitor | G17: Logged out | H17: Open /dashboard /billing /admin /project/create directly | I17: Logged-out visitor is redirected or shown auth-required state; no protected data is visible
A18: Pass | B18: GO-MAN-017 | C18: Auth | D18: Session persistence | E18: P1 | F18: Logged-in User | G18: User is logged in | H18: Refresh current page; close and reopen browser tab; revisit site | I18: Session remains valid if expected; user identity and nav state are stable
A19: Pass | B19: GO-MAN-018 | C19: Onboarding | D19: Start onboarding | E19: P0 | F19: Logged-in User | G19: Logged in as member | H19: Open onboarding page; begin onboarding flow | I19: Onboarding starts cleanly; first step is clear; progress is visible if expected
A20: Pass | B20: GO-MAN-019 | C20: Onboarding | D20: Complete required fields | E20: P0 | F20: Logged-in User | G20: Onboarding available | H20: Complete every required onboarding step with valid values; submit final step | I20: Profile is saved; completion state appears; user can proceed to CV generation
A21: Pass | B21: GO-MAN-020 | C21: Onboarding | D21: Validation errors | E21: P1 | F21: Logged-in User | G21: Onboarding available | H21: Leave required fields empty; enter invalid URLs; exceed long text limits; submit | I21: Helpful validation errors appear; entered valid data is preserved; user can correct and continue
A22: Pass | B22: GO-MAN-021 | C22: Onboarding | D22: Back/forward navigation | E22: P1 | F22: Logged-in User | G22: Onboarding in progress | H22: Move forward several steps; go back; edit previous values; move forward again | I22: Previously entered values persist; progress remains correct; no data loss
... A101: Not Run | B101: GO-MAN-100 | C101: Release | D101: Production readiness | E101: P0 | F101: Developer | G101: Pre-launch environment configured | H101: Verify env vars webhook URL success URL Firestore rules bootstrap secret and Polar token mode | I101: Production uses production Polar token/product IDs; webhook points to production domain; bootstrap secret removed; rules deployed

Sheet Known Issues
A1: # | B1: Issues | C1: Reproduction and root cause | D1: Status | E1: Files changed | F1: Test/evidence | G1: Final status
A2: 1 | B2: 1. Default filter on projects should be all statueses | C2: The project status filter already initializes to all appropriate statuses and retains later selection. | D2: RETEST | E2: None | F2: Existing project visibility/filter coverage; local /projects browser load | G2: Verified
A3: 2 | B3: 2. Save project doesn't work | C3: Create and edit save handlers already expose progress/errors and prevent duplicate submits. | D3: RETEST | E3: None | F3: Existing projects-route, form, and project-update tests | G3: Verified
A4: 3 | B4: 3. Make Budget optionally visible on projects that don't have a budget | C4: Optional budget paths already accept absence, remove a previous budget, and hide missing values. | D4: RETEST | E4: None | F4: Existing project create/update and budget utility tests | G4: Verified
A5: 4 | B5: 4. When user applies to a project, project creator cannot see the aplicant CV | C5: Authorized project owners/admins can access application CV snapshots; unrelated users cannot. | D5: RETEST | E5: None | F5: Existing application and CV authorization tests | G5: Verified
A6: 5 | B6: 5. Add ability to add User Profile image or a randomly generated image | C6: Email signups receive a persisted DiceBear avatar, Google users retain their provider photo, and Radix fallback initials render. There is no complete upload/replacement UI or approved storage/file-validation policy. | D6: IN REVIEW | E6: None | F6: Code audit of auth normalization, avatar generation, and avatar components | G6: Needs decision
A7: 6 | B7: 6. I want the ability to completely remove project if I create one and remove it later, not archive it only, but have the ability to completely remove it | C7: Owner/admin permanent delete, archive, explicit confirmation, and related application/user-reference cleanup already exist. | D7: RETEST | E7: None | F7: Existing project delete authorization/cleanup tests | G7: Verified
A8: 7 | B8: 7. Update Primary roles to inlcude actual skills or make it function similar to tags | C8: Fixed-option primary roles did not use the community directory. Primary role now accepts directory suggestions or a normalized custom tag. | D8: DONE | E8: src/app/onboarding/page.js, src/app/api/onboarding/route.js, src/components/profile/SkillSelector.jsx | F8: Onboarding persistence and skill-selector tests | G8: Fixed
A9: 8 | B9: 8. Upate the secondary roles to have suggestions but also have the ability to add tags | C9: Secondary roles were fixed chips only. They now use suggestions plus custom tags, case-insensitive deduplication, and an eight-role limit. | D9: DONE | E9: Same as #7 | F9: Onboarding normalization tests | G9: Fixed
A10: 9 | B10: 9. Update skill level to make more sense | C10: Persisted values were ambiguous labels. The stored IDs remain unchanged for compatibility, while UI labels/descriptions now explain Learning, Developing, Independent, Advanced, and Production-proven. | D10: DONE | E10: src/constants/onboarding.js, src/app/onboarding/page.js | F10: Production build and source review | G10: Fixed
A11: 10 | B11: 10. Make tools also use suggestions and tags | C11: Tools were fixed chips and could not cover normal names. They now provide common suggestions and custom tags while preserving spaces, punctuation, and commas during entry. | D11: DONE | E11: src/components/profile/SkillSelector.jsx, src/app/onboarding/page.js, src/app/api/onboarding/route.js | F11: CV input and onboarding normalization tests | G11: Fixed
A12: 11 | B12: 11. When I try to apply to a project when I don't have a subscription I cannot do it, there should be a prompt telling me to get a subscription in order to have the ability to apply to projects. | C12: Membership-required application messaging, /membership CTA, and server-side active-member enforcement already exist. | D12: RETEST | E12: None | F12: Existing application-create and membership-gate tests | G12: Verified
A13: 12 | B13: 12. I want to have the ability to remove people from a project | C13: Project owners/admins can remove non-owner members; server logic prevents owner/admin removal and updates approved applications. No new email is sent without an approved event. | D13: RETEST | E13: None | F13: Existing project-member route tests | G13: Verified
... A41: 40 | B41: 40. I want to make sure that the users that have joined go discord before their onbording process t onot have to leave a username. If they have not joined the GO discord yet then pelase make sure there is a link to join GO send to them in the follow up email. we'll decide later in which email but they must be a follow up. | C41: Discord username was labeled required and joined state was not modeled separately. Username is optional, joined state and invitation eligibility persist separately, and non-joined members see the safe GO invite link. The data hook exists, but no invitation email is enqueued until placement/copy are approved. | D41: RETEST | E41: src/constants/onboarding.js, src/app/onboarding/page.js, src/app/api/onboarding/route.js | F41: Onboarding persistence/no-completion-email tests; accessible labels in production build | G41: Partially fixed
A42: 41 | B42: Remove the mandatory AI requirement to complete the onboarding | C42: Remove the mandatory AI requirement to complete the onboarding | D42: DONE
A43: 42 | B43: Allow on thi sscreen the full scope of skills that are available in the BE | D43: DONE
A44: 43 | B44: I want to be able to choose any skill to be my primary | D44: DONE
A45: 44 | B45: Issues with overlap with Profile and GameDev Passport | C45: Make a list of all changes required first please | D45: TODO
A46: 45 | B46: There is a verify email but no verification email is sent we need to fix this logic.
A47: 46 | B47: Creator should decide if they will allow for the user to apply to the project again, please make sure to add a mandatory field for creators to have to select or explain why they have rejected a user. And inform users automatically when the project has moved to a different stage from hiring and thet they were not selected for this project at this time but encourage to follow the project and apply
A48: 47 | B48: I should
A49: 48
A50: 49
A51: 50
A52: 51
A53: 52
A54: 53
A55: 54
A56: 55
A57: 56
A58: 57
A59: 58
A60: 59
... A110: 109

Sheet QA Template
A1: Test ID | B1: Suite | C1: Feature | D1: Priority | E1: Persona | F1: Preconditions | G1: Steps | H1: Expected Result | I1: Status | J1: Actual Result | K1: Notes | L1: Evidence Link | M1: Run Date
A2: GO-MAN-001 | B2: Public Website | C2: Home page load | D2: P0 | E2: Visitor | F2: Production or local site is running | G2: Open the home page; wait for the page to fully load; check above-the-fold content; scroll to bottom | H2: Home page loads without console-visible broken UI; main brand/content is clear; no missing critical images; footer is reachable | I2: Not Run
A3: GO-MAN-002 | B3: Public Website | C3: Desktop navigation | D3: P0 | E3: Visitor | F3: Site is running on desktop viewport | G3: Open home page; click each main nav item; use browser back; repeat for logo/home link | H3: Every nav item routes to the expected page; no 404; active page content matches navigation label | I3: Not Run
A4: GO-MAN-003 | B4: Public Website | C4: Mobile navigation | D4: P0 | E4: Visitor | F4: Site is running on mobile viewport | G4: Resize to mobile or use phone; open mobile menu; tap every nav item; close and reopen menu | H4: Mobile menu is usable; links work; menu does not overlap content; menu can be dismissed | I4: Not Run
A5: GO-MAN-004 | B5: Public Website | C5: Landing CTAs | D5: P0 | E5: Visitor | F5: Site is running | G5: Open home page; click primary CTA; return; click secondary CTAs; check destination pages | H5: CTAs route to intended signup/pricing/contact/project pages; labels match destination intent | I5: Not Run
A6: GO-MAN-005 | B6: Public Website | C6: Responsive layout | D6: P1 | E6: Visitor | F6: Use desktop tablet and mobile widths | G6: Check home/pricing/projects/about/FAQ pages at 390px 768px and desktop widths | H6: No horizontal scrolling; text does not overlap; buttons fit; sections remain readable | I6: Not Run
A7: GO-MAN-006 | B7: Public Website | C7: Image and asset loading | D7: P1 | E7: Visitor | F7: Site is running | G7: Open key public pages; look for broken images/icons; refresh once | H7: Images/icons render correctly; no obvious layout jumps due to missing assets | I7: Not Run
A8: GO-MAN-007 | B8: Public Website | C8: FAQ page | D8: P1 | E8: Visitor | F8: FAQ page exists | G8: Open FAQ; expand/collapse each FAQ item; check links if present | H8: FAQ controls work; content is readable; links open expected destinations | I8: Not Run
A9: GO-MAN-008 | B9: Public Website | C9: About page | D9: P1 | E9: Visitor | F9: About page exists | G9: Open About; scan page content; test visible links/buttons | H9: About content is readable and current; links/buttons work; no typo-heavy or placeholder content | I9: Not Run
A10: GO-MAN-009 | B10: Public Website | C10: Pricing page | D10: P0 | E10: Visitor | F10: Polar products configured | G10: Open pricing page; inspect all tiers and intervals; toggle monthly/annual if available | H10: Pricing is understandable; member vs company benefits are clear; checkout buttons are visible | I10: Not Run
A11: GO-MAN-010 | B11: Public Website | C11: 404/not-found experience | D11: P2 | E11: Visitor | F11: Site is running | G11: Open a nonsense URL such as /this-page-does-not-exist | H11: User sees a graceful not-found or redirect experience; no raw error stack | I11: Not Run
A12: GO-MAN-011 | B12: Auth | C12: Signup flow | D12: P0 | E12: Visitor | F12: Test email available | G12: Open signup; create account; complete required fields; submit | H12: Account is created; user lands on expected next page; no duplicate or confusing messages | I12: Not Run
A13: GO-MAN-012 | B13: Auth | C13: Login flow | D13: P0 | E13: Free User | F13: Existing account available | G13: Open login; enter valid credentials; submit | H13: User logs in; protected nav/profile state appears; no unexpected redirect loop | I13: Not Run
... A101: GO-MAN-100 | B101: Release | C101: Production readiness | D101: P0 | E101: Developer | F101: Pre-launch environment configured | G101: Verify env vars webhook URL success URL Firestore rules bootstrap secret and Polar token mode | H101: Production uses production Polar token/product IDs; webhook points to production domain; bootstrap secret removed; rules deployed | I101: Not Run

Sheet Accounts
A1: Account | B1: Purpose | C1: Email
A2: Free email user | B2: Membership prompts, restricted project creation and onboarding | C2: kikerkov@gmail.com
A3: Free Google user | B3: Google login, redirect and profile tests | C3: mugi@mugi.mk
A4: Active Community member | B4: Applying to projects and upgrading to Business | C4: ivan.kikerkov@gmail.com
A5: Canceled Community member | B5: Renewal buttons and access after cancellation | C5: galacticomniworce@gmail.com
A6: Business Creator | B6: Own, create, edit and delete projects | C6: galacticomnivore@galacticomnivore.com
A7: Platform Admin | B7: Administrative permissions and owner/admin comparisons | C7: galacticadmin@gmail.com

Sheet Chart1 Website Test Suite V1.6 
A1: STATUS UPDATE GO WEBSITE 2.0 TEST SUITE RESULTS 29.07.2026
A3: Status | B3: Pass | C3: Blocked | D3: Fail | E3: Not Run | F3: Retest
A4: Pass | B4: 68
A5: Fail | D5: 9
A6: Retest | F6: 2
A7: Blocked | C7: 14
A8: Not Run | E8: 7
